{"route": {"routeIds": ["5332_120624"], "routeShortName": "G2", "routeLongName": "Liffey Valley SC - Spencer Dock"}, "directions": [{"directionId": "0", "headsign": "Liffey Valley SC", "stops": [{"stopId": "8220DB007890", "stopName": "Castleforbes Road", "stopCode": "7890", "lat": 53.348964, "lon": -6.231907, "stopSequence": 1, "arrivalTime": "05:15:00", "departureTime": "05:15:00"}, {"stopId": "8220DB007842", "stopName": "New Wapping Street", "stopCode": "7842", "lat": 53.347654, "lon": -6.235394, "stopSequence": 2, "arrivalTime": "05:16:22", "departureTime": "05:16:22"}, {"stopId": "8220DB007611", "stopName": "North Wall Quay", "stopCode": "7611", "lat": 53.34727, "lon": -6.23661, "stopSequence": 3, "arrivalTime": "05:16:45", "departureTime": "05:16:45"}, {"stopId": "8220DB007398", "stopName": "Convention Centre", "stopCode": "7398", "lat": 53.347499, "lon": -6.239853, "stopSequence": 4, "arrivalTime": "05:17:17", "departureTime": "05:17:17"}, {"stopId": "8220DB007397", "stopName": "Samuel Beckett Bridge", "stopCode": "7397", "lat": 53.347694, "lon": -6.2433, "stopSequence": 5, "arrivalTime": "05:17:52", "departureTime": "05:17:52"}, {"stopId": "8220DB006252", "stopName": "Sean O'Casey Bridge", "stopCode": "6252", "lat": 53.347965, "lon": -6.247044, "stopSequence": 6, "arrivalTime": "05:18:51", "departureTime": "05:18:51"}, {"stopId": "8220DB000303", "stopName": "Eden Quay", "stopCode": "303", "lat": 53.34806, "lon": -6.255992, "stopSequence": 7, "arrivalTime": "05:21:13", "departureTime": "05:21:13"}, {"stopId": "8220DB007889", "stopName": "Burgh Quay", "stopCode": "7889", "lat": 53.347076, "lon": -6.258135, "stopSequence": 8, "arrivalTime": "05:22:06", "departureTime": "05:22:06"}, {"stopId": "8220DB007891", "stopName": "Wellington Quay", "stopCode": "7891", "lat": 53.345428, "lon": -6.266584, "stopSequence": 9, "arrivalTime": "05:24:24", "departureTime": "05:24:24"}, {"stopId": "8220DB007888", "stopName": "Winetavern Street", "stopCode": "7888", "lat": 53.344561, "lon": -6.271891, "stopSequence": 10, "arrivalTime": "05:26:02", "departureTime": "05:26:02"}, {"stopId": "8220DB001937", "stopName": "High Street", "stopCode": "1937", "lat": 53.343088, "lon": -6.273152, "stopSequence": 11, "arrivalTime": "05:27:04", "departureTime": "05:27:04"}, {"stopId": "8220DB001938", "stopName": "Cornmarket", "stopCode": "1938", "lat": 53.342978, "lon": -6.276761, "stopSequence": 12, "arrivalTime": "05:27:56", "departureTime": "05:27:56"}, {"stopId": "8220DB001939", "stopName": "Thomas Street", "stopCode": "1939", "lat": 53.342998, "lon": -6.280665, "stopSequence": 13, "arrivalTime": "05:28:36", "departureTime": "05:28:36"}, {"stopId": "8220DB001940", "stopName": "Watling Street", "stopCode": "1940", "lat": 53.343539, "lon": -6.285734, "stopSequence": 14, "arrivalTime": "05:29:38", "departureTime": "05:29:38"}, {"stopId": "8220DB001941", "stopName": "James's Street", "stopCode": "1941", "lat": 53.343345, "lon": -6.289181, "stopSequence": 15, "arrivalTime": "05:30:19", "departureTime": "05:30:19"}, {"stopId": "8220DB001942", "stopName": "St James Hospital", "stopCode": "1942", "lat": 53.34215, "lon": -6.29468, "stopSequence": 16, "arrivalTime": "05:31:06", "departureTime": "05:31:06"}, {"stopId": "8220DB001943", "stopName": "Mount Brown", "stopCode": "1943", "lat": 53.3413732636991, "lon": -6.29834636571316, "stopSequence": 17, "arrivalTime": "05:31:33", "departureTime": "05:31:33"}, {"stopId": "8220DB001944", "stopName": "Old Kilmainham", "stopCode": "1944", "lat": 53.3406753265043, "lon": -6.3036154053404, "stopSequence": 18, "arrivalTime": "05:32:30", "departureTime": "05:32:30"}, {"stopId": "8220DB001945", "stopName": "Inchicore Library", "stopCode": "1945", "lat": 53.3405547841693, "lon": -6.30968740041896, "stopSequence": 19, "arrivalTime": "05:33:35", "departureTime": "05:33:35"}, {"stopId": "8220DB001946", "stopName": "Emmet Road", "stopCode": "1946", "lat": 53.340119, "lon": -6.316357, "stopSequence": 20, "arrivalTime": "05:34:35", "departureTime": "05:34:35"}, {"stopId": "8220DB001947", "stopName": "Inchicore Village", "stopCode": "1947", "lat": 53.339818, "lon": -6.317961, "stopSequence": 21, "arrivalTime": "05:34:50", "departureTime": "05:34:50"}, {"stopId": "8220DB002642", "stopName": "Grattan Crescent", "stopCode": "2642", "lat": 53.341209, "lon": -6.319739, "stopSequence": 22, "arrivalTime": "05:36:21", "departureTime": "05:36:21"}, {"stopId": "8220DB002643", "stopName": "Sarsfield Road", "stopCode": "2643", "lat": 53.34154, "lon": -6.320927, "stopSequence": 23, "arrivalTime": "05:37:03", "departureTime": "05:37:03"}, {"stopId": "8220DB002644", "stopName": "Sarsfield Medical", "stopCode": "2644", "lat": 53.3419905931282, "lon": -6.32738226562619, "stopSequence": 24, "arrivalTime": "05:37:53", "departureTime": "05:37:53"}, {"stopId": "8220DB002709", "stopName": "Longmeadows", "stopCode": "2709", "lat": 53.342992781435, "lon": -6.33348566501732, "stopSequence": 25, "arrivalTime": "05:38:38", "departureTime": "05:38:38"}, {"stopId": "8220DB002710", "stopName": "Ballyfermot Road", "stopCode": "2710", "lat": 53.342115, "lon": -6.339512, "stopSequence": 26, "arrivalTime": "05:39:25", "departureTime": "05:39:25"}, {"stopId": "8220DB002711", "stopName": "Markievicz Park", "stopCode": "2711", "lat": 53.341783, "lon": -6.341523, "stopSequence": 27, "arrivalTime": "05:39:45", "departureTime": "05:39:45"}, {"stopId": "8220DB002712", "stopName": "St Gabriel's School", "stopCode": "2712", "lat": 53.342459848185, "lon": -6.34556625983834, "stopSequence": 28, "arrivalTime": "05:40:26", "departureTime": "05:40:26"}, {"stopId": "8220DB002655", "stopName": "Ballyfermot Parade", "stopCode": "2655", "lat": 53.3421381592165, "lon": -6.35284757646734, "stopSequence": 29, "arrivalTime": "05:41:49", "departureTime": "05:41:49"}, {"stopId": "8220DB002656", "stopName": "Ballyfermot", "stopCode": "2656", "lat": 53.342624, "lon": -6.358716, "stopSequence": 30, "arrivalTime": "05:42:53", "departureTime": "05:42:53"}, {"stopId": "8220DB002668", "stopName": "Ballyfermot Community Centre", "stopCode": "2668", "lat": 53.342983, "lon": -6.363283, "stopSequence": 31, "arrivalTime": "05:44:02", "departureTime": "05:44:02"}, {"stopId": "8220DB002672", "stopName": "Cleggan Park", "stopCode": "2672", "lat": 53.3433589409048, "lon": -6.36777417735812, "stopSequence": 32, "arrivalTime": "05:44:46", "departureTime": "05:44:46"}, {"stopId": "8230DB002673", "stopName": "Cherry Orchard IE", "stopCode": "2673", "lat": 53.3437794112348, "lon": -6.3728945596684, "stopSequence": 33, "arrivalTime": "05:45:28", "departureTime": "05:45:28"}, {"stopId": "8230DB002206", "stopName": "Cherry Orchard Hosp", "stopCode": "2206", "lat": 53.3441867930205, "lon": -6.37574767124231, "stopSequence": 34, "arrivalTime": "05:45:50", "departureTime": "05:45:50"}, {"stopId": "8230DB004798", "stopName": "Whitethorn Crescent", "stopCode": "4798", "lat": 53.345614, "lon": -6.38092, "stopSequence": 35, "arrivalTime": "05:46:37", "departureTime": "05:46:37"}, {"stopId": "8230DB002674", "stopName": "Coldcut Road", "stopCode": "2674", "lat": 53.347496, "lon": -6.389111, "stopSequence": 36, "arrivalTime": "05:47:50", "departureTime": "05:47:50"}, {"stopId": "8230DB002675", "stopName": "Harelawn", "stopCode": "2675", "lat": 53.34778895067, "lon": -6.39552753886545, "stopSequence": 37, "arrivalTime": "05:48:38", "departureTime": "05:48:38"}, {"stopId": "8230DB002124", "stopName": "Neilstown Road", "stopCode": "2124", "lat": 53.3469584164072, "lon": -6.39793187307251, "stopSequence": 38, "arrivalTime": "05:49:06", "departureTime": "05:49:06"}, {"stopId": "8230DB002125", "stopName": "Harelawn Green", "stopCode": "2125", "lat": 53.3455867762438, "lon": -6.39819357526104, "stopSequence": 39, "arrivalTime": "05:49:26", "departureTime": "05:49:26"}, {"stopId": "8230DB002126", "stopName": "Rowlagh", "stopCode": "2126", "lat": 53.343935440152, "lon": -6.39837562988944, "stopSequence": 40, "arrivalTime": "05:49:51", "departureTime": "05:49:51"}, {"stopId": "8230DB002127", "stopName": "Collinstown College", "stopCode": "2127", "lat": 53.341572, "lon": -6.399035, "stopSequence": 41, "arrivalTime": "05:50:26", "departureTime": "05:50:26"}, {"stopId": "8230DB002128", "stopName": "Neilstown Avenue", "stopCode": "2128", "lat": 53.3396666624101, "lon": -6.39975201801215, "stopSequence": 42, "arrivalTime": "05:51:01", "departureTime": "05:51:01"}, {"stopId": "8230DB002129", "stopName": "Moorefield Drive", "stopCode": "2129", "lat": 53.335728, "lon": -6.400305, "stopSequence": 43, "arrivalTime": "05:52:09", "departureTime": "05:52:09"}, {"stopId": "8230DB004797", "stopName": "St Ronan's Avenue", "stopCode": "4797", "lat": 53.337065157306, "lon": -6.40549559350714, "stopSequence": 44, "arrivalTime": "05:53:26", "departureTime": "05:53:26"}, {"stopId": "8230DB007473", "stopName": "Foxdene Gardens", "stopCode": "7473", "lat": 53.3390526490492, "lon": -6.4082746923561, "stopSequence": 45, "arrivalTime": "05:54:28", "departureTime": "05:54:28"}, {"stopId": "8230DB002681", "stopName": "Fonthill Road", "stopCode": "2681", "lat": 53.3417450847511, "lon": -6.40797917237562, "stopSequence": 46, "arrivalTime": "05:55:01", "departureTime": "05:55:01"}, {"stopId": "8230DB004691", "stopName": "Rowlagh Crescent", "stopCode": "4691", "lat": 53.3435086159179, "lon": -6.40744789046173, "stopSequence": 47, "arrivalTime": "05:55:17", "departureTime": "05:55:17"}, {"stopId": "8230DB002682", "stopName": "St Mark's Grove", "stopCode": "2682", "lat": 53.3455923408494, "lon": -6.40666431435993, "stopSequence": 48, "arrivalTime": "05:55:36", "departureTime": "05:55:36"}, {"stopId": "8230DB004796", "stopName": "Glenfield", "stopCode": "4796", "lat": 53.347363, "lon": -6.406013, "stopSequence": 49, "arrivalTime": "05:56:08", "departureTime": "05:56:08"}, {"stopId": "8230DB004690", "stopName": "Fonthill Retail Park", "stopCode": "4690", "lat": 53.349509439251, "lon": -6.40519639715848, "stopSequence": 50, "arrivalTime": "05:56:50", "departureTime": "05:56:50"}, {"stopId": "8230DB004411", "stopName": "Shancastle Park", "stopCode": "4411", "lat": 53.3509677182543, "lon": -6.40469131774696, "stopSequence": 51, "arrivalTime": "05:57:09", "departureTime": "05:57:09"}, {"stopId": "8230DB007754", "stopName": "Clayton Hotel", "stopCode": "7754", "lat": 53.353797, "lon": -6.401191, "stopSequence": 52, "arrivalTime": "05:58:15", "departureTime": "05:58:15"}, {"stopId": "8230DB008029", "stopName": "Liffey Valley Shopping Centre", "stopCode": "8029", "lat": 53.354429, "lon": -6.392694, "stopSequence": 53, "arrivalTime": "05:59:48", "departureTime": "05:59:48"}], "shape": [[53.3489617595632, -6.23192749038566], [53.3493004, -6.2318653], [53.349338, -6.231859], [53.3494249, -6.2318424], [53.3495298, -6.2318231], [53.3500009, -6.2317365], [53.3500869, -6.2330736], [53.3502135, -6.2350226], [53.3496527242527, -6.23511972105264], [53.3493104, -6.2351791], [53.3488022, -6.2352667], [53.3487266, -6.2352802], [53.3486944, -6.2352859], [53.3486244, -6.2352982], [53.3483429028834, -6.23534765270872], [53.3481893, -6.2353745], [53.3481392, -6.2353834], [53.3480874, -6.2353925], [53.347658541823, -6.23546822971232], [53.3474685, -6.2355018], [53.3473643, -6.2355202], [53.3473315, -6.2355263], [53.3472836, -6.2355351], [53.3472916, -6.2356714], [53.3472944, -6.2357193], [53.3472984, -6.235787], [53.3473325537773, -6.2363658915966], [53.3473375694757, -6.23645107778105], [53.3473466997768, -6.23660589350605], [53.3473639, -6.2368952], [53.3474312, -6.2380243], [53.3474403, -6.2381696], [53.3474859, -6.2389002], [53.3474986, -6.2391038], [53.3475115, -6.2393091], [53.3475413, -6.2397866], [53.3475436660994, -6.23982523192042], [53.3475452, -6.239849], [53.3475272, -6.2403547], [53.3475488, -6.2407436], [53.3476047, -6.2409435], [53.3476075, -6.2409839], [53.3476116, -6.2410438], [53.3476215, -6.2411872], [53.3476367, -6.2414143], [53.3476397, -6.2414578], [53.3476436, -6.2415165], [53.3476576, -6.2417239], [53.3476787, -6.2420384], [53.3477026044696, -6.24239614228179], [53.3477594, -6.2432397], [53.3477611371379, -6.24326631251664], [53.347792, -6.2437256], [53.3477947, -6.2437655], [53.3477995, -6.2438382], [53.3478044, -6.2439109], [53.3478133, -6.2440423], [53.3479365, -6.2458779], [53.3479413, -6.2459481], [53.3479516, -6.2461021], [53.3479594, -6.2462345], [53.3479635, -6.2463044], [53.3479721, -6.2464498], [53.3480034204257, -6.24698323771278], [53.3480066472749, -6.2470372905805], [53.3480130777464, -6.2471465831749], [53.3480222, -6.2473009], [53.3480351, -6.2475197], [53.3480569, -6.2478901], [53.3480596, -6.2479357], [53.3480909, -6.2484688], [53.3480955484399, -6.24854671882527], [53.3480822, -6.2488114], [53.3481061, -6.2491715], [53.3481413, -6.2496891], [53.3481596, -6.250019], [53.3482229, -6.2511496], [53.3482318, -6.2513087], [53.3482352, -6.2513854], [53.3482429, -6.2515609], [53.3482469, -6.2516519], [53.3482492, -6.2517575], [53.3482429, -6.2527501], [53.3482417, -6.2547685], [53.3482232, -6.2549478], [53.3481994, -6.2551245], [53.3481923, -6.255177], [53.3481223, -6.2557925], [53.3480942600511, -6.25600514851843], [53.3480465, -6.2563689], [53.3479587, -6.25704], [53.34795, -6.2570928], [53.3479076, -6.2573124], [53.3478966, -6.2573397], [53.347883, -6.2573634], [53.3478615, -6.257388], [53.3478274, -6.2574072], [53.3474254, -6.25734], [53.3473856, -6.2573355], [53.3473126, -6.2573289], [53.3471864, -6.2579467], [53.3471306953427, -6.25821699347981], [53.3470516, -6.2586017], [53.3470448, -6.2586348], [53.3470086, -6.258792], [53.3469680362511, -6.25889296740714], [53.3469832124523, -6.25890280845936], [53.3469735, -6.2589457], [53.3469466, -6.259063], [53.3469351, -6.25911], [53.3470334, -6.2591395], [53.3474169, -6.2593446], [53.3474404, -6.2593571], [53.3475212, -6.2593927], [53.3475419, -6.2593063], [53.3475525, -6.2592619], [53.3475905, -6.2591013], [53.3476208, -6.2589759], [53.3477048, -6.2586239], [53.3477594, -6.2583905], [53.3477794717471, -6.25829296192667], [53.3479096, -6.2576656], [53.3479201, -6.2576104], [53.3479618, -6.2573793], [53.3479705, -6.2573305], [53.3480063, -6.2571141], [53.3481675535786, -6.25605075500768], [53.3482121, -6.2557574], [53.3482604, -6.2551553], [53.3482797, -6.2549447], [53.3482934, -6.2547718], [53.3482967, -6.2547314], [53.3482904, -6.2541802], [53.3482902172457, -6.25387665047543], [53.3482898, -6.2530001], [53.3482936, -6.2527502], [53.3483092, -6.2521408], [53.3483104, -6.2519893], [53.3483092, -6.2518496], [53.3483086, -6.2517561], [53.3483064, -6.2516236], [53.3483035, -6.2515446], [53.348295, -6.2513894], [53.3482891, -6.251278], [53.3482837, -6.251167], [53.3482782, -6.2510436], [53.3482237259188, -6.25011522745682], [53.3482131, -6.2499334], [53.3481819, -6.2491868], [53.3481527, -6.2488002], [53.348129, -6.2487038], [53.3480955484399, -6.24854671882527], [53.3480822, -6.2488114], [53.3481061, -6.2491715], [53.3481413, -6.2496891], [53.3481596, -6.250019], [53.3482229, -6.2511496], [53.3482318, -6.2513087], [53.3482352, -6.2513854], [53.3482429, -6.2515609], [53.3482469, -6.2516519], [53.3482492, -6.2517575], [53.3482429, -6.2527501], [53.3482417, -6.2547685], [53.3482232, -6.2549478], [53.3481994, -6.2551245], [53.3481923, -6.255177], [53.3481223, -6.2557925], [53.3480942600511, -6.25600514851843], [53.3480465, -6.2563689], [53.3479587, -6.25704], [53.34795, -6.2570928], [53.3479076, -6.2573124], [53.3478966, -6.2573397], [53.347883, -6.2573634], [53.3478615, -6.257388], [53.3478274, -6.2574072], [53.3474254, -6.25734], [53.3473856, -6.2573355], [53.3473126, -6.2573289], [53.3471864, -6.2579467], [53.3471398478824, -6.25817234840039], [53.3471306953427, -6.25821699347981], [53.3470516, -6.2586017], [53.3470448, -6.2586348], [53.3470086, -6.258792], [53.3469680362511, -6.25889296740714], [53.3469832124523, -6.25890280845936], [53.3469735, -6.2589457], [53.3469466, -6.259063], [53.3469351, -6.25911], [53.3468875, -6.2592521], [53.3468857645346, -6.25928225847429], [53.3468825, -6.2593428], [53.3468544040091, -6.25946244640592], [53.3467444, -6.2599335], [53.3467107, -6.2600776], [53.3466501, -6.2603368], [53.3465901, -6.2605934], [53.3465574, -6.2607335], [53.3465103, -6.2609349], [53.3464614, -6.2611437], [53.3463163, -6.2617647], [53.3462881, -6.2618852], [53.3462199927911, -6.26219543443596], [53.3461284, -6.2626132], [53.3460565, -6.2629547], [53.3459631, -6.2634759], [53.3458906, -6.2639071], [53.3457208, -6.264978], [53.3457055, -6.2651043], [53.3455634, -6.2660649], [53.3454845870872, -6.26659925572947], [53.3453905, -6.267239], [53.3453317, -6.2676299], [53.3452274, -6.2689481], [53.3451298, -6.2699885], [53.3449729, -6.2721187], [53.3449389, -6.2721078], [53.3448926, -6.2720478], [53.3448597, -6.2720187], [53.3445573062468, -6.27192550062998], [53.3443729, -6.2718685], [53.3442063, -6.2717957], [53.3441722, -6.2717854], [53.3440809, -6.2717739], [53.3440445, -6.2717693], [53.3437932, -6.2717532], [53.3435412, -6.2717782], [53.343271, -6.2717497], [53.3432253, -6.2717456], [53.3430552, -6.2717623], [53.3430334, -6.2717627], [53.3429541, -6.2717643], [53.3428701, -6.2717822], [53.3428804, -6.2720247], [53.342923, -6.2723064], [53.343078, -6.2731005], [53.3430800935858, -6.27311416371243], [53.3430861276186, -6.27315234701223], [53.3431931, -6.2738269], [53.3432452, -6.2741552], [53.3432825, -6.2745111], [53.3432829, -6.2746088], [53.3432804, -6.2747173], [53.3432727, -6.2748756], [53.3432208, -6.2752026], [53.3431798, -6.2754554], [53.3430802, -6.2759454], [53.3430679, -6.2760296], [53.3430668, -6.2761703], [53.3429974322268, -6.27652265734362], [53.3429533649268, -6.2767471827057], [53.3429423889207, -6.27680282755103], [53.3429187, -6.2769237], [53.3428815, -6.2771035], [53.3428658, -6.2771805], [53.3428228, -6.2774154], [53.3428047, -6.2775367], [53.3427956, -6.2776271], [53.3427901, -6.2777499], [53.3427853, -6.2779668], [53.3427856, -6.278177], [53.3427928, -6.2784979], [53.3428129, -6.2791156], [53.3428815, -6.2796082], [53.3429186, -6.2798366], [53.3429858, -6.2802443], [53.3430472184375, -6.28054657695164], [53.3430619385642, -6.28061916338712], [53.3430972, -6.280792], [53.3431612, -6.2811023], [53.3431839, -6.281212], [53.3432164, -6.2813603], [53.3432444, -6.2815223], [53.3432565, -6.2816428], [53.3433051, -6.2821298], [53.3433547, -6.2830145], [53.3433938, -6.2837568], [53.343425, -6.2842958], [53.343448, -6.2845154], [53.3434529, -6.2845799], [53.3434801, -6.284856], [53.3435233, -6.285423], [53.3435287798254, -6.28550118097467], [53.3435444825701, -6.28572483787329], [53.34355, -6.2858], [53.3435623, -6.2859733], [53.3435591, -6.2862805], [53.3435303, -6.2868824], [53.3435258, -6.2869856], [53.3434988, -6.2875824], [53.3434815, -6.2879175], [53.3434731, -6.2881454], [53.3434619, -6.2883533], [53.3434565944631, -6.28846873644197], [53.343445, -6.2887223], [53.343429, -6.288927], [53.3434123812238, -6.28917605377274], [53.3434112472688, -6.28919382376084], [53.3434006, -6.2893545], [53.3433658, -6.2895512], [53.3433517, -6.2896307], [53.3433338, -6.2896959], [53.3432784, -6.2899126], [53.3432506, -6.2900292], [53.3431724, -6.2904124], [53.3431434, -6.2905462], [53.3431395, -6.2905708], [53.3430806, -6.290709], [53.3430648, -6.2907906], [53.3429838, -6.2912114], [53.3428832, -6.2916679], [53.3426968, -6.2925291], [53.3425607, -6.2931669], [53.3425492, -6.2932214], [53.3425222, -6.2933431], [53.3424796, -6.2935087], [53.3424527, -6.2936294], [53.3423877, -6.2938774], [53.3423564, -6.294006], [53.342353, -6.2941815], [53.3422376865989, -6.2946190666983], [53.3422195661341, -6.29468769357098], [53.3421256, -6.2950447], [53.341966, -6.2955287], [53.3418953, -6.2957211], [53.3418449, -6.2959328], [53.3416325, -6.2969566], [53.3415619, -6.2973326], [53.3415084, -6.2975951], [53.3414987, -6.2976774], [53.3414811, -6.297829], [53.3414472, -6.2981404], [53.3414294110109, -6.29834314278618], [53.3414279956605, -6.29835986996801], [53.3414002, -6.2986782], [53.3413361, -6.2992152], [53.3413242, -6.2993145], [53.3413038, -6.2994858], [53.34114, -6.3004749], [53.3411149, -6.3006497], [53.341021, -6.3012675], [53.3409361, -6.3018323], [53.3408991, -6.3020782], [53.3407841, -6.302843], [53.340779, -6.3028816], [53.3407229, -6.3033034], [53.3407162, -6.3033536], [53.3407083, -6.303444], [53.340694586957, -6.30360072585523], [53.3406936, -6.3036126], [53.3407015, -6.3039017], [53.3407274, -6.3042036], [53.3407463, -6.3046673], [53.3407206, -6.305383], [53.3406988, -6.3059908], [53.340688, -6.3062908], [53.3406298, -6.3074437], [53.3406317, -6.3076594], [53.3406192, -6.3081675], [53.3406006, -6.3089227], [53.3405954971867, -6.30910849376959], [53.3405806544771, -6.30966533297794], [53.3405800641905, -6.30968936778539], [53.340579, -6.3097328], [53.3405793, -6.3098746], [53.3405806, -6.3104457], [53.3406104, -6.3110003], [53.3406343, -6.3112712], [53.3406532, -6.3115175], [53.3406735, -6.3117962], [53.3407085, -6.3123823], [53.3407016, -6.3126821], [53.3406866, -6.3128822], [53.3406491, -6.3131698], [53.3406088, -6.3134287], [53.3405468, -6.3137804], [53.3405037, -6.3140069], [53.340435, -6.3144763], [53.3404092021728, -6.3146676029082], [53.3403026, -6.3154585], [53.3402888, -6.3155624], [53.3402647, -6.3157507], [53.3401748568206, -6.31636296069529], [53.3401724614992, -6.31637962229599], [53.3401483, -6.3165451], [53.3400906, -6.3168792], [53.340081, -6.3169326], [53.3400677, -6.316981], [53.3400156, -6.3172034], [53.3398606, -6.3178653], [53.3398412963311, -6.31795860131278], [53.3398383696963, -6.31797301642203], [53.3397285, -6.3185097], [53.3396313, -6.3189043], [53.3395101, -6.3193039], [53.3394073, -6.3196427], [53.3393674, -6.3198472], [53.3393687, -6.3199306], [53.3393738, -6.3200101], [53.3393913, -6.3201112], [53.339447, -6.3205098], [53.3394549, -6.3205664], [53.3394865, -6.3207727], [53.3395244, -6.321039], [53.3396357, -6.3209479], [53.3397278, -6.3208782], [53.3401126, -6.3205602], [53.3403268, -6.3203933], [53.3404852, -6.3202755], [53.3406314, -6.3202125], [53.3407705, -6.3201504], [53.340871, -6.3200831], [53.340988, -6.3199546], [53.3410915, -6.3198079], [53.3411542818252, -6.31969609815086], [53.3411605582407, -6.31968483033868], [53.3412396, -6.3195441], [53.341416, -6.3192433], [53.3414746, -6.3191342], [53.3415603, -6.3191921], [53.3415946, -6.3192408], [53.341619, -6.3193073], [53.3416379, -6.3194521], [53.3416108, -6.3199914], [53.3416043584467, -6.32010568446113], [53.3415899, -6.3203677], [53.3415662, -6.3208548], [53.3415602579394, -6.32097458278484], [53.3415594827679, -6.32099131967069], [53.3415352, -6.3214931], [53.3414829, -6.3223001], [53.3414624, -6.3229569], [53.341471, -6.3231487], [53.3414851, -6.3232639], [53.3415266, -6.3236278], [53.3416032, -6.3240149], [53.3416341, -6.3241518], [53.3417269, -6.3244917], [53.3418803, -6.3249931], [53.3419383, -6.3252437], [53.3419606, -6.3255164], [53.3419835, -6.3257768], [53.3420147, -6.3259864], [53.3420176, -6.3264675], [53.34202, -6.3265979], [53.3420572342005, -6.32735139532559], [53.3420583485771, -6.32737294152317], [53.3420973, -6.328157], [53.3421303, -6.3285856], [53.3421903, -6.3289236], [53.3422362, -6.3294749], [53.3422876, -6.3299813], [53.3423496, -6.3304223], [53.3424158, -6.3307276], [53.3426237, -6.3316508], [53.3427711980603, -6.33229014109212], [53.3427922, -6.3323805], [53.3430126, -6.3333212], [53.3430374496902, -6.33343276905732], [53.3430423704018, -6.33345460230276], [53.3431258, -6.3338269], [53.3431825, -6.3341386], [53.3432032, -6.3342525], [53.3432466, -6.3345703], [53.3432668, -6.3347932], [53.3432729, -6.3348603], [53.3432913, -6.3351822], [53.3432974, -6.3354654], [53.34329, -6.3357418], [53.3432719, -6.3359653], [53.3432332, -6.3362959], [53.3431768, -6.3366377], [53.3431373, -6.3368433], [53.3431026, -6.3369975], [53.3430554, -6.3372075], [53.3429591, -6.3375621], [53.3428848, -6.3377962], [53.342753, -6.3381594], [53.3425841, -6.338541], [53.3425543362028, -6.33859827602172], [53.3424853, -6.3387315], [53.3423864, -6.338922], [53.3422152, -6.3393308], [53.3421365751734, -6.33951904453765], [53.3421314568239, -6.33953142228525], [53.3420738, -6.3396699], [53.3420212, -6.3398628], [53.3419724, -6.3401111], [53.3419152, -6.3404566], [53.3418992, -6.3405718], [53.3418773, -6.3407281], [53.3418705, -6.3407969], [53.3418471, -6.3410341], [53.3418433, -6.3411087], [53.3418319, -6.3413274], [53.3418291851309, -6.34151476895792], [53.3418274, -6.3416511], [53.3418348400507, -6.34187008412674], [53.341838, -6.3419596], [53.3418757, -6.3423107], [53.3418912, -6.3424542], [53.3419331, -6.3426904], [53.341992, -6.3429661], [53.3420765, -6.3432999], [53.3421104, -6.3434102], [53.3421882, -6.343664], [53.3422774, -6.3439776], [53.3423589, -6.3443519], [53.3424087, -6.344668], [53.3424481, -6.3450502], [53.3424656, -6.3452426], [53.3424836875603, -6.34554848284773], [53.3424847124732, -6.34556495396324], [53.3424898, -6.3458204], [53.3424916, -6.3459122], [53.3424786, -6.3463766], [53.3424555, -6.3467903], [53.3424367052193, -6.34705880572215], [53.3424027, -6.3475483], [53.3423674, -6.3481173], [53.3423582, -6.3482561], [53.3423508, -6.3483846], [53.342275, -6.3484086], [53.3421703, -6.3485037], [53.3420984, -6.3486452], [53.3420726, -6.3487659], [53.3420883, -6.3489083], [53.3421266, -6.34903], [53.3422049, -6.3491665], [53.3422734, -6.3492306], [53.3422682, -6.3493715], [53.3422591, -6.3495212], [53.3422375, -6.3498742], [53.3422269, -6.3500485], [53.3422022, -6.3505597], [53.3421799, -6.3513073], [53.342163, -6.3521394], [53.3421663, -6.3523972], [53.3421733, -6.3526025], [53.342182, -6.3528219], [53.342207325654, -6.35318653790016], [53.3422103, -6.3532277], [53.3422466, -6.3537447], [53.3423005, -6.3544755], [53.3423191, -6.3547273], [53.3424192, -6.3561995], [53.3424699, -6.3567683], [53.3425172, -6.3572993], [53.3425396, -6.357551], [53.3426004, -6.3582331], [53.3426126, -6.3583703], [53.3426368, -6.358687], [53.3426453, -6.358787], [53.3426693, -6.3590839], [53.3426913, -6.3593556], [53.3427073, -6.359554], [53.3427433, -6.3599352], [53.342787, -6.360399], [53.3428276, -6.3609439], [53.3428367, -6.3610652], [53.3428886, -6.3617618], [53.3429306, -6.3622476], [53.3429397, -6.3623528], [53.3429633, -6.3626262], [53.3430161, -6.3632375], [53.3430195392341, -6.3632728956719], [53.3430205908587, -6.36328405861466], [53.3430633, -6.363717], [53.3430668, -6.363754], [53.3430811, -6.363926], [53.3430926, -6.3640657], [53.3431022, -6.3641823], [53.3431522, -6.3647828], [53.343175, -6.3650572], [53.3431872, -6.365209], [53.3432064, -6.3654396], [53.3432303, -6.3656917], [53.3432453, -6.365864], [53.343277, -6.3662274], [53.3433121, -6.3666001], [53.34334, -6.3669085], [53.3433549, -6.3670724], [53.3434098226642, -6.36767908110936], [53.3434126, -6.3677092], [53.3434452, -6.3681728], [53.3434504, -6.3682392], [53.3434711, -6.3685036], [53.3435246, -6.369186], [53.3435446, -6.3694345], [53.3435529, -6.3695377], [53.3435884, -6.3699709], [53.3435941, -6.3700408], [53.3436194, -6.3703223], [53.3436373, -6.3705348], [53.3436471, -6.370652], [53.3436554, -6.3707529], [53.3436676, -6.3708972], [53.3437002, -6.3712958], [53.3437034, -6.371329], [53.3437635, -6.372072], [53.3438538885487, -6.37287092959825], [53.3438609835205, -6.37292446172702], [53.3438648, -6.3729527], [53.3438789222911, -6.37306660769924], [53.3439106, -6.3733205], [53.3439328, -6.3734807], [53.34397, -6.3737348], [53.3440828, -6.3746762], [53.3441179, -6.3749139], [53.3441837, -6.3753603], [53.3442369125188, -6.37567580991464], [53.3442444687499, -6.37572028586546], [53.3442909, -6.3759939], [53.344363, -6.3763762], [53.3443688, -6.376407], [53.3444049, -6.3765836], [53.3444527, -6.3768157], [53.3445177146394, -6.37707395513137], [53.344575, -6.377308], [53.3446844, -6.3777238], [53.344771, -6.3780526], [53.3448041, -6.3781785], [53.3448838, -6.3784816], [53.3450021, -6.3788368], [53.3450974, -6.3790435], [53.34517, -6.3791694], [53.3452265, -6.3792522], [53.3453615, -6.3794113], [53.3454702, -6.379602], [53.3455008, -6.3796789], [53.3455182, -6.3797228], [53.3455486, -6.3798142], [53.3455808, -6.3799213], [53.3455663, -6.3801572], [53.3455695, -6.3802726], [53.3455743, -6.3804631], [53.3456, -6.380713], [53.3456299705274, -6.38089160357988], [53.3456658, -6.3810355], [53.3457484, -6.3813326], [53.3459185, -6.3818535], [53.3461398, -6.3823801], [53.3464008, -6.3829052], [53.3465694, -6.3832444], [53.3467791, -6.3836516], [53.3469867, -6.3841609], [53.3471056807887, -6.38456556117761], [53.347121, -6.3846171], [53.3471774, -6.3848578], [53.3472346, -6.3851486], [53.3472762, -6.3854061], [53.3473163, -6.3858057], [53.3474008, -6.3868077], [53.3475533, -6.3884245], [53.3475617, -6.3885442], [53.3475808571501, -6.38873374576962], [53.3476025, -6.3889467], [53.3476157362798, -6.38918471798878], [53.3476168501608, -6.3892038082927], [53.3476399, -6.3896146], [53.347653, -6.3898498], [53.3476583, -6.3899445], [53.3476693, -6.3901362], [53.3476857, -6.3904728], [53.3477755, -6.3923357], [53.3478296, -6.3929777], [53.3478132, -6.3936634], [53.347811, -6.3940602], [53.3478439, -6.395014], [53.3478612906379, -6.39552061070178], [53.3478628230896, -6.39556629743572], [53.3478730270571, -6.39585980576086], [53.3478913, -6.3963855], [53.3478979, -6.3965766], [53.3479219, -6.3971399], [53.347934, -6.3975001], [53.3478994, -6.3975128], [53.3478662, -6.3975405], [53.3478382, -6.3975811], [53.3478195, -6.3976242], [53.3478068, -6.3976727], [53.3478003, -6.3977285], [53.3477979, -6.3977833], [53.3477108, -6.3977997], [53.3474627, -6.3978468], [53.3472101, -6.3979018], [53.3469650649579, -6.39797714208662], [53.3467596, -6.3980401], [53.3463048, -6.3981312], [53.3458064, -6.3982262], [53.3455896801591, -6.39824852044886], [53.3453602, -6.3982722], [53.345028, -6.3983259], [53.345022, -6.3982757], [53.3450069, -6.3982313], [53.3449842, -6.3981971], [53.3449562, -6.3981765], [53.3449258, -6.3981718], [53.3448939, -6.3981848], [53.3448665, -6.398215], [53.3448468, -6.398259], [53.3448372, -6.3983115], [53.3448386, -6.3983665], [53.3443479, -6.3984208], [53.3441106, -6.3984471], [53.3439402763046, -6.39846599851638], [53.3438815, -6.3984724], [53.3438175, -6.3984816], [53.3434607, -6.3985331], [53.3429581, -6.398627], [53.3428978, -6.3986383], [53.3428835, -6.3985812], [53.3428588, -6.3985352], [53.3428263, -6.3985056], [53.3427898, -6.3984957], [53.3427534, -6.3985066], [53.3427212, -6.3985371], [53.3426968, -6.3985837], [53.3426831, -6.3986412], [53.3426815, -6.398703], [53.3426435, -6.3987183], [53.342397, -6.3988176], [53.3418925, -6.3989646], [53.3415810849896, -6.39909748997819], [53.3413706, -6.3991873], [53.3411756, -6.39928], [53.3409436, -6.399408], [53.3407349, -6.3995321], [53.3407105, -6.3994737], [53.3406812, -6.3994403], [53.3406472, -6.399424], [53.3406118, -6.3994264], [53.3405786, -6.3994473], [53.3405511, -6.3994846], [53.3405319, -6.3995345], [53.3405231, -6.399592], [53.3405254, -6.3996511], [53.3404678, -6.3996623], [53.3402085, -6.3997129], [53.3398376, -6.3997988], [53.3396776259003, -6.39984009581876], [53.3393773, -6.3999175], [53.3389509, -6.399996], [53.338781, -6.4000272], [53.3384663, -6.4000345], [53.3383581, -6.4000126], [53.338256, -6.399992], [53.3381749, -6.3999756], [53.3381694, -6.3999365], [53.3381616, -6.3999084], [53.338151, -6.399883], [53.3381297, -6.3998507], [53.3381132, -6.3998352], [53.3380952, -6.3998248], [53.3380762, -6.3998201], [53.3380517, -6.3998224], [53.3380207, -6.3998402], [53.3379959, -6.3998703], [53.3379774, -6.3999112], [53.3379664, -6.3999613], [53.3379643, -6.399993], [53.3379655, -6.4000249], [53.3378061, -6.4000579], [53.3376519, -6.4000934], [53.3374034, -6.4001051], [53.3372073, -6.4000965], [53.3370502503541, -6.40008542952685], [53.3366489, -6.4000568], [53.3363895, -6.4000966], [53.3363529, -6.4001067], [53.3361617, -6.4001593], [53.3358352, -6.4003165], [53.3357475573635, -6.40036872631347], [53.3355685, -6.4004755], [53.3353125, -6.4006685], [53.3351647, -6.4008318], [53.3350987, -6.4009047], [53.3349345, -6.4010999], [53.3348055, -6.4012997], [53.3347333, -6.4014515], [53.3348562, -6.4015186], [53.3349699, -6.401632], [53.3350283, -6.4017022], [53.3350642, -6.4017528], [53.3351228, -6.4018497], [53.335262, -6.40215], [53.3354367, -6.4025859], [53.3354607, -6.4026458], [53.3355705, -6.4029372], [53.3357198, -6.4032914], [53.335841, -6.403585], [53.3359338, -6.4037726], [53.3360648, -6.4039761], [53.3362975, -6.4043171], [53.3365992, -6.4047501], [53.336776, -6.4050041], [53.3369102, -6.4051967], [53.3370763631176, -6.40545606772083], [53.3371821, -6.4056206], [53.3373576, -6.4058542], [53.3375936, -6.4062144], [53.3376979, -6.40641], [53.3378053, -6.4066565], [53.3378258, -6.4067109], [53.3378639, -6.4068804], [53.3378923, -6.4070365], [53.337872, -6.4072832], [53.3378594, -6.4076366], [53.3378476, -6.408], [53.3378794, -6.408008], [53.337929, -6.4080149], [53.3380075, -6.4080259], [53.3380744, -6.4080309], [53.3385299, -6.4080872], [53.3387604530314, -6.40809122430765], [53.3390137, -6.4080954], [53.3390484744455, -6.40809520934052], [53.3392052, -6.4080935], [53.3392928, -6.4080926], [53.339794, -6.4081045], [53.340331, -6.4080793], [53.3407872, -6.4080102], [53.3409655, -6.4079794], [53.3411755, -6.4079413], [53.3415787, -6.4078766], [53.3417266881281, -6.40784668369891], [53.3419734, -6.4077966], [53.3423106, -6.4077007], [53.3429848, -6.4074913], [53.3434898633601, -6.40730525282831], [53.3435286465662, -6.40729102073752], [53.3440776, -6.4070888], [53.3443747, -6.4069794], [53.3450183, -6.4067405], [53.3452651821263, -6.40664328091576], [53.345569179861, -6.40652341183191], [53.3460772, -6.406323], [53.3473115, -6.4058786], [53.3473449018928, -6.40586690484926], [53.3477168777923, -6.40573636922717], [53.3478917, -6.4056749], [53.3481963, -6.4055586], [53.3483011, -6.4055948], [53.3484273, -6.4056008], [53.3484523, -6.4056531], [53.3484823, -6.4056925], [53.3485265, -6.4057247], [53.3485599, -6.4057343], [53.3485956, -6.4057322], [53.3486491, -6.405704], [53.3486926, -6.4056508], [53.3487184, -6.4055949], [53.3487354, -6.4055292], [53.3488806, -6.4053675], [53.3489426, -6.4053019], [53.3489873, -6.4052821], [53.3491379, -6.4052261], [53.3494982814172, -6.40510423735932], [53.3495568912066, -6.40508438483685], [53.3495696, -6.4050801], [53.3496361, -6.4050535], [53.3498222, -6.404996], [53.3501192, -6.4048857], [53.3504733, -6.404746], [53.3507479, -6.4046376], [53.3508969, -6.4045938], [53.3509500827201, -6.40457822733752], [53.3511292, -6.4045254], [53.3515106, -6.4044133], [53.3518689, -6.4043361], [53.3520756, -6.404304], [53.3525511, -6.4042538], [53.3531195, -6.404167], [53.3532085, -6.404185], [53.3535712, -6.4042582], [53.3536103, -6.4043212], [53.353665, -6.4043735], [53.3537413, -6.4044023], [53.3538195, -6.4043882], [53.3538816, -6.4043422], [53.3539383, -6.4042595], [53.3539637, -6.4041975], [53.3539818, -6.4041285], [53.3539918, -6.4040549], [53.3539907, -6.4039374], [53.3539693, -6.4038259], [53.3539433, -6.4037566], [53.3539114, -6.4037004], [53.3538188, -6.4034774], [53.3537871, -6.4033004], [53.3537853, -6.4031094], [53.3537837, -6.4029426], [53.3537786, -6.4023944], [53.3537553418776, -6.40119308184853], [53.3537515, -6.4009889], [53.3537516, -6.4009398], [53.3537531, -6.4005859], [53.3537851, -6.4005333], [53.3538081, -6.4004689], [53.3538207, -6.4003966], [53.3538218, -6.4003214], [53.3538115, -6.4002482], [53.3537986, -6.4002027], [53.3537812, -6.4001616], [53.3537441, -6.3998559], [53.3537408, -6.3997927], [53.3537269, -6.3995301], [53.3537007, -6.3982021], [53.3536677, -6.3971117], [53.3536469, -6.396418], [53.3537553, -6.3959336], [53.3538571, -6.3954605], [53.3538745, -6.3954191], [53.3539437, -6.3952908], [53.3539704029867, -6.39524110825511], [53.3540128, -6.3951625], [53.3543316, -6.3945255], [53.3544308, -6.3943782], [53.3544857, -6.3943762], [53.3545369, -6.3943436], [53.3545787, -6.3942843], [53.3546037, -6.3942157], [53.3546156, -6.3941382], [53.3546135, -6.394058], [53.3545974, -6.3939825], [53.3545688, -6.393918], [53.3546621, -6.3939218], [53.3548164, -6.3935964], [53.3548945, -6.3934316], [53.3549324, -6.3933319], [53.3549971, -6.3931756], [53.3550500737232, -6.39302689034907], [53.3550922, -6.3928376], [53.3551894, -6.3926815], [53.3552417, -6.3926099], [53.3552633, -6.3926014], [53.3553017, -6.3925625], [53.3553311, -6.3925057], [53.3553495, -6.3924304], [53.3553519, -6.3923492], [53.355338, -6.3922712], [53.3553095, -6.3922054], [53.3552695, -6.3921593], [53.3552227, -6.392138], [53.3551743, -6.392144], [53.3550883, -6.3921069], [53.3550318, -6.3920535], [53.3549656, -6.3919477], [53.3548243, -6.3917483], [53.3546883, -6.3915277], [53.3545654, -6.3913614], [53.3545358, -6.3913513], [53.3545182, -6.3913605], [53.3544545, -6.3914598], [53.3544217, -6.391511], [53.3543873, -6.3915271], [53.3543429, -6.3914868], [53.3541022424745, -6.39110180917311], [53.353919, -6.3908082], [53.3538662, -6.3907667], [53.3538085, -6.3907546], [53.3537477, -6.3907868], [53.3536861, -6.390886], [53.3537837, -6.3910402], [53.3538286, -6.3911609], [53.3546027335488, -6.39238723362358]], "finalStop": {"stopId": "8230DB008029", "stopName": "Liffey Valley Shopping Centre", "stopCode": "8029", "lat": 53.354429, "lon": -6.392694, "stopSequence": 53, "arrivalTime": "05:59:48", "departureTime": "05:59:48"}}, {"directionId": "1", "headsign": "Spencer Dock", "stops": [{"stopId": "8230DB008061", "stopName": "Liffey Valley SC", "stopCode": "8061", "lat": 53.354298, "lon": -6.392354, "stopSequence": 1, "arrivalTime": "05:01:00", "departureTime": "05:01:00"}, {"stopId": "8230DB07755", "stopName": "Clayton Hotel", "stopCode": "7755", "lat": 53.353546, "lon": -6.40123, "stopSequence": 2, "arrivalTime": "05:02:51", "departureTime": "05:02:51"}, {"stopId": "8230DB004688", "stopName": "Shancastle Park", "stopCode": "4688", "lat": 53.3504093402239, "lon": -6.40460702189292, "stopSequence": 3, "arrivalTime": "05:03:53", "departureTime": "05:03:53"}, {"stopId": "8230DB004689", "stopName": "Fonthill Retail Park", "stopCode": "4689", "lat": 53.3476991984373, "lon": -6.40559441371749, "stopSequence": 4, "arrivalTime": "05:04:32", "departureTime": "05:04:32"}, {"stopId": "8230DB004410", "stopName": "St Mark's Grove", "stopCode": "4410", "lat": 53.3452489649675, "lon": -6.40652692613806, "stopSequence": 5, "arrivalTime": "05:04:56", "departureTime": "05:04:56"}, {"stopId": "8230DB002678", "stopName": "Rowlagh", "stopCode": "2678", "lat": 53.343504006989, "lon": -6.40710263290625, "stopSequence": 6, "arrivalTime": "05:05:12", "departureTime": "05:05:12"}, {"stopId": "8230DB002679", "stopName": "Rowlagh Crescent", "stopCode": "2679", "lat": 53.341501, "lon": -6.407753, "stopSequence": 7, "arrivalTime": "05:05:51", "departureTime": "05:05:51"}, {"stopId": "8230DB002680", "stopName": "Foxdene Gardens", "stopCode": "2680", "lat": 53.338761172745, "lon": -6.40798520807897, "stopSequence": 8, "arrivalTime": "05:06:44", "departureTime": "05:06:44"}, {"stopId": "8230DB002676", "stopName": "Wood Avens", "stopCode": "2676", "lat": 53.3366231165782, "lon": -6.40470120662439, "stopSequence": 9, "arrivalTime": "05:07:27", "departureTime": "05:07:27"}, {"stopId": "8230DB002118", "stopName": "Neilstown Road", "stopCode": "2118", "lat": 53.335624, "lon": -6.400564, "stopSequence": 10, "arrivalTime": "05:08:33", "departureTime": "05:08:33"}, {"stopId": "8230DB002119", "stopName": "Saint Peter's Junior National School", "stopCode": "2119", "lat": 53.337048, "lon": -6.40018, "stopSequence": 11, "arrivalTime": "05:09:02", "departureTime": "05:09:02"}, {"stopId": "8230DB002120", "stopName": "Collinstown College", "stopCode": "2120", "lat": 53.341163, "lon": -6.399426, "stopSequence": 12, "arrivalTime": "05:10:25", "departureTime": "05:10:25"}, {"stopId": "8230DB002121", "stopName": "Rowlagh", "stopCode": "2121", "lat": 53.3438755786503, "lon": -6.3986031558769, "stopSequence": 13, "arrivalTime": "05:11:20", "departureTime": "05:11:20"}, {"stopId": "8230DB002123", "stopName": "St Mark's Avenue", "stopCode": "2123", "lat": 53.3471760338791, "lon": -6.39807391277744, "stopSequence": 14, "arrivalTime": "05:12:26", "departureTime": "05:12:26"}, {"stopId": "8230DB002685", "stopName": "Coldcut Road", "stopCode": "2685", "lat": 53.347955, "lon": -6.395852, "stopSequence": 15, "arrivalTime": "05:13:11", "departureTime": "05:13:11"}, {"stopId": "8230DB002686", "stopName": "Coldcut Road", "stopCode": "2686", "lat": 53.347652, "lon": -6.388713, "stopSequence": 16, "arrivalTime": "05:14:17", "departureTime": "05:14:17"}, {"stopId": "8230DB007510", "stopName": "Coldcut Crescent", "stopCode": "7510", "lat": 53.347196, "lon": -6.384513, "stopSequence": 17, "arrivalTime": "05:14:55", "departureTime": "05:14:55"}, {"stopId": "8230DB004799", "stopName": "Ballyfermot Road", "stopCode": "4799", "lat": 53.3451937376096, "lon": -6.37907372188316, "stopSequence": 18, "arrivalTime": "05:16:00", "departureTime": "05:16:00"}, {"stopId": "8230DB002205", "stopName": "Cherry Orchard Hosp", "stopCode": "2205", "lat": 53.344590643431, "lon": -6.37702396338742, "stopSequence": 19, "arrivalTime": "05:16:22", "departureTime": "05:16:22"}, {"stopId": "8230DB002687", "stopName": "Cherry Orchard IE", "stopCode": "2687", "lat": 53.343961, "lon": -6.373038, "stopSequence": 20, "arrivalTime": "05:16:55", "departureTime": "05:16:55"}, {"stopId": "8220DB002688", "stopName": "Cleggan Park", "stopCode": "2688", "lat": 53.343463, "lon": -6.368191, "stopSequence": 21, "arrivalTime": "05:17:31", "departureTime": "05:17:31"}, {"stopId": "8220DB002689", "stopName": "Blackditch Drive", "stopCode": "2689", "lat": 53.343106, "lon": -6.363744, "stopSequence": 22, "arrivalTime": "05:18:04", "departureTime": "05:18:04"}, {"stopId": "8220DB002696", "stopName": "Ballyfermot", "stopCode": "2696", "lat": 53.342688, "lon": -6.358804, "stopSequence": 23, "arrivalTime": "05:19:19", "departureTime": "05:19:19"}, {"stopId": "8220DB002697", "stopName": "Ballyfermot Parade", "stopCode": "2697", "lat": 53.342278, "lon": -6.353173, "stopSequence": 24, "arrivalTime": "05:20:19", "departureTime": "05:20:19"}, {"stopId": "8220DB002713", "stopName": "St Gabriel's School", "stopCode": "2713", "lat": 53.3424806534687, "lon": -6.34706729796392, "stopSequence": 25, "arrivalTime": "05:21:19", "departureTime": "05:21:19"}, {"stopId": "8220DB002714", "stopName": "Markievicz Park", "stopCode": "2714", "lat": 53.3419051123135, "lon": -6.34186321373163, "stopSequence": 26, "arrivalTime": "05:22:08", "departureTime": "05:22:08"}, {"stopId": "8220DB002715", "stopName": "O'Hogan Road", "stopCode": "2715", "lat": 53.342613, "lon": -6.338661, "stopSequence": 27, "arrivalTime": "05:22:40", "departureTime": "05:22:40"}, {"stopId": "8220DB002716", "stopName": "Sarsfield Road", "stopCode": "2716", "lat": 53.3428406256586, "lon": -6.33224505599933, "stopSequence": 28, "arrivalTime": "05:23:29", "departureTime": "05:23:29"}, {"stopId": "8220DB002718", "stopName": "St Mary's Avenue", "stopCode": "2718", "lat": 53.3422822606705, "lon": -6.32767121720049, "stopSequence": 29, "arrivalTime": "05:24:04", "departureTime": "05:24:04"}, {"stopId": "8220DB002719", "stopName": "Woodfield Place", "stopCode": "2719", "lat": 53.3416457682976, "lon": -6.32011193943824, "stopSequence": 30, "arrivalTime": "05:25:10", "departureTime": "05:25:10"}, {"stopId": "8220DB001989", "stopName": "Inchicore Village", "stopCode": "1989", "lat": 53.339706, "lon": -6.318987, "stopSequence": 31, "arrivalTime": "05:27:10", "departureTime": "05:27:10"}, {"stopId": "8220DB001990", "stopName": "Myra Cottages", "stopCode": "1990", "lat": 53.340472781795, "lon": -6.31469157313953, "stopSequence": 32, "arrivalTime": "05:28:13", "departureTime": "05:28:13"}, {"stopId": "8220DB001992", "stopName": "Inchicore Library", "stopCode": "1992", "lat": 53.3406544981518, "lon": -6.30911277701976, "stopSequence": 33, "arrivalTime": "05:29:33", "departureTime": "05:29:33"}, {"stopId": "8220DB001993", "stopName": "Old Kilmainham", "stopCode": "1993", "lat": 53.3408, "lon": -6.30466, "stopSequence": 34, "arrivalTime": "05:30:25", "departureTime": "05:30:25"}, {"stopId": "8220DB001994", "stopName": "Mount Brown", "stopCode": "1994", "lat": 53.3414239628449, "lon": -6.29938060050009, "stopSequence": 35, "arrivalTime": "05:31:13", "departureTime": "05:31:13"}, {"stopId": "8220DB001995", "stopName": "James's Luas", "stopCode": "1995", "lat": 53.342675, "lon": -6.293218, "stopSequence": 36, "arrivalTime": "05:32:11", "departureTime": "05:32:11"}, {"stopId": "8220DB001996", "stopName": "James's Street", "stopCode": "1996", "lat": 53.34356, "lon": -6.288482, "stopSequence": 37, "arrivalTime": "05:33:17", "departureTime": "05:33:17"}, {"stopId": "8220DB001997", "stopName": "Watling Street", "stopCode": "1997", "lat": 53.34364, "lon": -6.28542, "stopSequence": 38, "arrivalTime": "05:33:55", "departureTime": "05:33:55"}, {"stopId": "8220DB001998", "stopName": "Thomas Street", "stopCode": "1998", "lat": 53.34314, "lon": -6.280494, "stopSequence": 39, "arrivalTime": "05:35:15", "departureTime": "05:35:15"}, {"stopId": "8220DB001999", "stopName": "Cornmarket", "stopCode": "1999", "lat": 53.343119, "lon": -6.27659, "stopSequence": 40, "arrivalTime": "05:36:21", "departureTime": "05:36:21"}, {"stopId": "8220DB002001", "stopName": "High Street", "stopCode": "2001", "lat": 53.343311, "lon": -6.273653, "stopSequence": 41, "arrivalTime": "05:37:11", "departureTime": "05:37:11"}, {"stopId": "8220DB007883", "stopName": "Ormond Quay", "stopCode": "7883", "lat": 53.346058, "lon": -6.268496, "stopSequence": 42, "arrivalTime": "05:40:25", "departureTime": "05:40:25"}, {"stopId": "8220DB007359", "stopName": "Eden Quay", "stopCode": "7359", "lat": 53.347924, "lon": -6.257985, "stopSequence": 43, "arrivalTime": "05:43:54", "departureTime": "05:43:54"}, {"stopId": "8220DB000407", "stopName": "Custom House", "stopCode": "407", "lat": 53.348335, "lon": -6.253893, "stopSequence": 44, "arrivalTime": "05:45:10", "departureTime": "05:45:10"}, {"stopId": "8220DB002498", "stopName": "IFSC", "stopCode": "2498", "lat": 53.34828, "lon": -6.25027, "stopSequence": 45, "arrivalTime": "05:46:24", "departureTime": "05:46:24"}, {"stopId": "8220DB002499", "stopName": "Sean O'Casey Bridge", "stopCode": "2499", "lat": 53.348128, "lon": -6.247128, "stopSequence": 46, "arrivalTime": "05:46:57", "departureTime": "05:46:57"}, {"stopId": "8220DB002500", "stopName": "Samuel Beckett Bridge", "stopCode": "2500", "lat": 53.347788, "lon": -6.24238, "stopSequence": 47, "arrivalTime": "05:47:53", "departureTime": "05:47:53"}, {"stopId": "8220DB002501", "stopName": "North Wall Quay", "stopCode": "2501", "lat": 53.347376, "lon": -6.236359, "stopSequence": 48, "arrivalTime": "05:49:16", "departureTime": "05:49:16"}, {"stopId": "8220DB002502", "stopName": "New Wapping Street", "stopCode": "2502", "lat": 53.34913, "lon": -6.2353, "stopSequence": 49, "arrivalTime": "05:50:24", "departureTime": "05:50:24"}, {"stopId": "8220DB007890", "stopName": "Castleforbes Road", "stopCode": "7890", "lat": 53.348964, "lon": -6.231907, "stopSequence": 50, "arrivalTime": "05:51:49", "departureTime": "05:51:49"}], "shape": [[53.3544322436428, -6.39211716561021], [53.3546749519592, -6.39250155684823], [53.3548019, -6.3927025], [53.3548447, -6.392718], [53.3548732, -6.3926972], [53.3549028, -6.3926288], [53.3549064, -6.3925832], [53.3549132, -6.3925155], [53.3549052, -6.3924215], [53.3548668, -6.3923249], [53.3545302, -6.3917811], [53.3545073, -6.3916833], [53.354513, -6.3916246], [53.3545286, -6.391579], [53.3545584, -6.3915596], [53.3545892, -6.3915577], [53.3546843, -6.3916467], [53.354809541233, -6.39184951770921], [53.3549449, -6.3920682], [53.3550358, -6.3922663], [53.3550651, -6.3923849], [53.3550746, -6.3924646], [53.3550861, -6.3926117], [53.3550922, -6.3928376], [53.3550500737232, -6.39302689034907], [53.3549971, -6.3931756], [53.3549324, -6.3933319], [53.3548945, -6.3934316], [53.3548164, -6.3935964], [53.3546621, -6.3939218], [53.3545688, -6.393918], [53.3545299, -6.3938704], [53.3544845, -6.3938439], [53.3544364, -6.393841], [53.35439, -6.3938621], [53.3543443, -6.3939126], [53.3543113, -6.3939857], [53.3542949, -6.3940711], [53.354296, -6.3941608], [53.3542447, -6.3943765], [53.3541032, -6.3946949], [53.353924, -6.3950279], [53.3538651, -6.3951262], [53.3537014, -6.395441], [53.3536139, -6.3955883], [53.3535601, -6.3955651], [53.3535171, -6.3955662], [53.3534819, -6.3955803], [53.3534474, -6.3956071], [53.3534154, -6.3956473], [53.3533906, -6.3956956], [53.3533742, -6.3957439], [53.3533606, -6.3958158], [53.3533578, -6.3958882], [53.3533652, -6.3959599], [53.3533776, -6.396012], [53.3533955, -6.3960595], [53.3534089, -6.3960858], [53.3534457, -6.3961353], [53.3534748, -6.3963945], [53.3534875, -6.3967263], [53.3534942, -6.3970105], [53.353561, -6.3998646], [53.3535493, -6.4001077], [53.3535137, -6.400161], [53.353488, -6.4002285], [53.3534741, -6.4003051], [53.353473, -6.4003852], [53.3534895, -6.40048], [53.3535239, -6.4005603], [53.3535625, -6.4008146], [53.353572, -6.4009412], [53.3535818, -6.4010721], [53.3535851821071, -6.40122434229852], [53.3536057, -6.4021047], [53.3536156, -6.4029573], [53.3536173, -6.4031049], [53.3536203, -6.40336], [53.3536091, -6.4035907], [53.3535904, -6.403713], [53.3535581, -6.4037765], [53.3535295, -6.4038712], [53.353436, -6.4040094], [53.3532285, -6.4041127], [53.3531195, -6.404167], [53.3525511, -6.4042538], [53.3520756, -6.404304], [53.3518689, -6.4043361], [53.3515106, -6.4044133], [53.3511292, -6.4045254], [53.350955604638, -6.40457662607728], [53.3508969, -6.4045938], [53.3507479, -6.4046376], [53.3504733, -6.404746], [53.350425990015, -6.40476464583155], [53.3501192, -6.4048857], [53.3498222, -6.404996], [53.3496361, -6.4050535], [53.3495696, -6.4050801], [53.3494982814172, -6.40510423735932], [53.3491379, -6.4052261], [53.3489873, -6.4052821], [53.3489426, -6.4053019], [53.3487208, -6.4053091], [53.3486927, -6.4052485], [53.3486635, -6.405209], [53.3486345, -6.4051842], [53.3486033, -6.4051691], [53.3485504, -6.4051664], [53.3484998, -6.4051909], [53.3484545, -6.4052426], [53.3484213, -6.4053157], [53.3484031, -6.4053775], [53.3482916, -6.405467], [53.3481963, -6.4055586], [53.3478917, -6.4056749], [53.3477168777923, -6.40573636922717], [53.3473449018928, -6.40586690484926], [53.3473115, -6.4058786], [53.3460772, -6.406323], [53.3455723155033, -6.40652219468198], [53.3452843441085, -6.40663570735177], [53.3452651821263, -6.40664328091576], [53.3450183, -6.4067405], [53.3443747, -6.4069794], [53.3440776, -6.4070888], [53.3435286465662, -6.40729102073752], [53.3434998961204, -6.40730155340765], [53.3434898633601, -6.40730525282831], [53.3429848, -6.4074913], [53.3423106, -6.4077007], [53.3419734, -6.4077966], [53.3417353086186, -6.40784495137127], [53.3415787, -6.4078766], [53.3415088082092, -6.40788780760482], [53.3411755, -6.4079413], [53.3409655, -6.4079794], [53.3407872, -6.4080102], [53.340331, -6.4080793], [53.339794, -6.4081045], [53.3392928, -6.4080926], [53.3392052, -6.4080935], [53.3390518639141, -6.40809519104729], [53.3390137, -6.4080954], [53.338765416845, -6.40809130695041], [53.3385299, -6.4080872], [53.3381248, -6.4078275], [53.3380902, -6.4077649], [53.3380335, -6.4076478], [53.3379553, -6.4073181], [53.3379374, -6.4071844], [53.3378923, -6.4070365], [53.3378639, -6.4068804], [53.3378258, -6.4067109], [53.3378053, -6.4066565], [53.3376979, -6.40641], [53.3375936, -6.4062144], [53.3373576, -6.4058542], [53.3371821, -6.4056206], [53.3370821775691, -6.40546506565491], [53.3369102, -6.4051967], [53.336776, -6.4050041], [53.3365992, -6.4047501], [53.3362975, -6.4043171], [53.3360648, -6.4039761], [53.3359338, -6.4037726], [53.335841, -6.403585], [53.3357198, -6.4032914], [53.3355705, -6.4029372], [53.3354607, -6.4026458], [53.3354367, -6.4025859], [53.335262, -6.40215], [53.3351228, -6.4018497], [53.3350642, -6.4017528], [53.3350283, -6.4017022], [53.3349699, -6.401632], [53.3348562, -6.4015186], [53.3347333, -6.4014515], [53.3348055, -6.4012997], [53.3349345, -6.4010999], [53.3350987, -6.4009047], [53.3351647, -6.4008318], [53.3353125, -6.4006685], [53.3355685, -6.4004755], [53.3356061003687, -6.40045305594237], [53.3357425475705, -6.4003717420895], [53.3358352, -6.4003165], [53.3361617, -6.4001593], [53.3363529, -6.4001067], [53.3363895, -6.4000966], [53.3366489, -6.4000568], [53.3370478451154, -6.40008526139849], [53.3372073, -6.4000965], [53.3374034, -6.4001051], [53.3376519, -6.4000934], [53.3378061, -6.4000579], [53.3379655, -6.4000249], [53.3379776, -6.4000829], [53.3379944, -6.4001206], [53.3380165, -6.4001496], [53.3380425, -6.4001678], [53.3380696, -6.4001739], [53.338091, -6.4001704], [53.3381175, -6.400155], [53.3381362, -6.4001349], [53.3381566, -6.4000984], [53.33817, -6.400054], [53.3381751, -6.4000158], [53.3381749, -6.3999756], [53.338256, -6.399992], [53.3383581, -6.4000126], [53.3384663, -6.4000345], [53.338781, -6.4000272], [53.3389509, -6.399996], [53.3393773, -6.3999175], [53.3396747419546, -6.39984085298488], [53.3398376, -6.3997988], [53.3402085, -6.3997129], [53.3404678, -6.3996623], [53.3405254, -6.3996511], [53.340537, -6.3997009], [53.3405563, -6.3997431], [53.3405822, -6.3997744], [53.3406122, -6.3997922], [53.340644, -6.399795], [53.3406681, -6.3997868], [53.3406924, -6.399768], [53.3407177, -6.3997323], [53.3407356, -6.3996856], [53.3407445, -6.3996322], [53.3407349, -6.3995321], [53.3409436, -6.399408], [53.3411423993337, -6.39929829102581], [53.3411756, -6.39928], [53.3413706, -6.3991873], [53.3415809221672, -6.39909758010455], [53.3418925, -6.3989646], [53.342397, -6.3988176], [53.3426435, -6.3987183], [53.3426815, -6.398703], [53.3426893, -6.3987518], [53.3427047, -6.3987951], [53.3427266, -6.3988299], [53.3427533, -6.3988534], [53.3427828, -6.3988639], [53.3428128, -6.3988604], [53.3428455, -6.3988398], [53.3428727, -6.3988028], [53.3428916, -6.3987535], [53.3429002, -6.3986968], [53.3428978, -6.3986383], [53.3429581, -6.398627], [53.3434607, -6.3985331], [53.3438175, -6.3984816], [53.3438600427999, -6.39847547752267], [53.3438815, -6.3984724], [53.3439389348254, -6.39846615277221], [53.3441106, -6.3984471], [53.3443479, -6.3984208], [53.3448386, -6.3983665], [53.3448503, -6.3984153], [53.3448708, -6.3984552], [53.3448979, -6.3984818], [53.3449286, -6.3984924], [53.3449598, -6.3984857], [53.344988, -6.3984625], [53.3450102, -6.3984253], [53.345024, -6.3983781], [53.345028, -6.3983259], [53.3453602, -6.3982722], [53.3455887105665, -6.39824862531525], [53.3458064, -6.3982262], [53.3463048, -6.3981312], [53.3467596, -6.3980401], [53.3469633929267, -6.3979776711755], [53.3471581088656, -6.39791777430861], [53.3472101, -6.3979018], [53.3474627, -6.3978468], [53.3477108, -6.3977997], [53.3477979, -6.3977833], [53.3478166, -6.3978624], [53.3478418, -6.3979212], [53.3478752, -6.3979644], [53.3479145, -6.3979902], [53.3479651, -6.3979953], [53.3479938, -6.397985], [53.3480145, -6.3979733], [53.3480494, -6.3979307], [53.3480766, -6.3978743], [53.3480922, -6.3978118], [53.348097, -6.3977444], [53.3480926, -6.3976868], [53.3480803, -6.3976326], [53.348061, -6.3975851], [53.3480359, -6.3975464], [53.3480076, -6.3975194], [53.3479766, -6.3975034], [53.347934, -6.3975001], [53.3479219, -6.3971399], [53.3478979, -6.3965766], [53.3478913, -6.3963855], [53.3478730270571, -6.39585980576086], [53.3478701062045, -6.39577678628458], [53.3478612906379, -6.39552061070178], [53.3478439, -6.395014], [53.347811, -6.3940602], [53.3478132, -6.3936634], [53.3478296, -6.3929777], [53.3478543, -6.3922964], [53.3478519, -6.3921555], [53.3478444, -6.3917223], [53.3477936, -6.3907495], [53.3477606, -6.3901164], [53.3477593, -6.3899337], [53.3477431, -6.3898323], [53.3476523, -6.3892603], [53.3476025, -6.3889467], [53.3475808571501, -6.38873374576962], [53.3475764618591, -6.38869073623458], [53.3475617, -6.3885442], [53.3475533, -6.3884245], [53.3474008, -6.3868077], [53.3473163, -6.3858057], [53.3472762, -6.3854061], [53.3472346, -6.3851486], [53.3471774, -6.3848578], [53.347121, -6.3846171], [53.3471110098248, -6.38458365259953], [53.3471056807887, -6.38456556117761], [53.3469867, -6.3841609], [53.3467791, -6.3836516], [53.3465694, -6.3832444], [53.3464008, -6.3829052], [53.3461398, -6.3823801], [53.3459185, -6.3818535], [53.3457484, -6.3813326], [53.3456658, -6.3810355], [53.3456299705274, -6.38089160357988], [53.3456, -6.380713], [53.3455743, -6.3804631], [53.3455695, -6.3802726], [53.3455663, -6.3801572], [53.3455815, -6.3799308], [53.3455871, -6.379763], [53.3455898, -6.3796836], [53.3455935, -6.3795779], [53.3454798, -6.3795024], [53.3453615, -6.3794113], [53.3452265, -6.3792522], [53.34517, -6.3791694], [53.3451472232564, -6.37912998531369], [53.3450974, -6.3790435], [53.3450021, -6.3788368], [53.3448838, -6.3784816], [53.3448041, -6.3781785], [53.344771, -6.3780526], [53.3446844, -6.3777238], [53.344575, -6.377308], [53.3445222644464, -6.37709274135062], [53.3445177146394, -6.37707395513137], [53.3444527, -6.3768157], [53.3444049, -6.3765836], [53.3443688, -6.376407], [53.344363, -6.3763762], [53.3442909, -6.3759939], [53.3442444687499, -6.37572028586546], [53.3441837, -6.3753603], [53.3441179, -6.3749139], [53.3440828, -6.3746762], [53.34397, -6.3737348], [53.3439328, -6.3734807], [53.3439106, -6.3733205], [53.3438789222911, -6.37306660769924], [53.3438648, -6.3729527], [53.3438607208757, -6.37292249346555], [53.3438538885487, -6.37287092959825], [53.3437635, -6.372072], [53.3437034, -6.371329], [53.3437002, -6.3712958], [53.3436676, -6.3708972], [53.3436554, -6.3707529], [53.3436471, -6.370652], [53.3436373, -6.3705348], [53.3436194, -6.3703223], [53.3435941, -6.3700408], [53.3435884, -6.3699709], [53.3435529, -6.3695377], [53.3435446, -6.3694345], [53.3435246, -6.369186], [53.3434711, -6.3685036], [53.3434504, -6.3682392], [53.3434452, -6.3681728], [53.3434126, -6.3677092], [53.3433549, -6.3670724], [53.34334, -6.3669085], [53.3433121, -6.3666001], [53.343277, -6.3662274], [53.3432453, -6.365864], [53.3432303, -6.3656917], [53.3432064, -6.3654396], [53.3431872, -6.365209], [53.343175, -6.3650572], [53.3431522, -6.3647828], [53.3431022, -6.3641823], [53.3430926, -6.3640657], [53.3430811, -6.363926], [53.3430668, -6.363754], [53.3430655727684, -6.36374153764482], [53.3430633, -6.363717], [53.3430195392341, -6.3632728956719], [53.3430161, -6.3632375], [53.3429633, -6.3626262], [53.3429397, -6.3623528], [53.3429306, -6.3622476], [53.3428886, -6.3617618], [53.3428367, -6.3610652], [53.3428276, -6.3609439], [53.342787, -6.360399], [53.3427433, -6.3599352], [53.3427073, -6.359554], [53.3426913, -6.3593556], [53.3426693, -6.3590839], [53.3426460815868, -6.35879726695044], [53.3426453, -6.358787], [53.3426368, -6.358687], [53.3426126, -6.3583703], [53.3426004, -6.3582331], [53.3425396, -6.357551], [53.3425172, -6.3572993], [53.3424699, -6.3567683], [53.3424192, -6.3561995], [53.3423191, -6.3547273], [53.3423005, -6.3544755], [53.3422466, -6.3537447], [53.3422103, -6.3532277], [53.3422090853973, -6.35321156021365], [53.342207325654, -6.35318653790016], [53.342182, -6.3528219], [53.3421733, -6.3526025], [53.3421663, -6.3523972], [53.342163, -6.3521394], [53.3421799, -6.3513073], [53.3422022, -6.3505597], [53.3422269, -6.3500485], [53.3422375, -6.3498742], [53.3422591, -6.3495212], [53.3422682, -6.3493715], [53.3422734, -6.3492306], [53.3423409, -6.3492127], [53.3424209, -6.3491527], [53.3424378, -6.3491329], [53.3425056, -6.3490529], [53.3425668, -6.3488844], [53.342565, -6.3487772], [53.342545, -6.3486774], [53.3424967, -6.3485362], [53.3424287, -6.3484292], [53.3423508, -6.3483846], [53.3423582, -6.3482561], [53.3423674, -6.3481173], [53.3424027, -6.3475483], [53.3424367052193, -6.34705880572215], [53.3424373859735, -6.34704838968062], [53.3424555, -6.3467903], [53.3424786, -6.3463766], [53.3424916, -6.3459122], [53.3424898, -6.3458204], [53.3424847124732, -6.34556495396324], [53.3424656, -6.3452426], [53.3424481, -6.3450502], [53.3424087, -6.344668], [53.3423589, -6.3443519], [53.3422774, -6.3439776], [53.3421882, -6.343664], [53.3421104, -6.3434102], [53.3420765, -6.3432999], [53.341992, -6.3429661], [53.3419331, -6.3426904], [53.3418912, -6.3424542], [53.3418757, -6.3423107], [53.341838, -6.3419596], [53.3418348400507, -6.34187008412674], [53.3418274, -6.3416511], [53.3418290976971, -6.34152430963199], [53.3418319, -6.3413274], [53.3418433, -6.3411087], [53.3418471, -6.3410341], [53.3418705, -6.3407969], [53.3418773, -6.3407281], [53.3418992, -6.3405718], [53.3419152, -6.3404566], [53.3419724, -6.3401111], [53.3420212, -6.3398628], [53.3420738, -6.3396699], [53.3421314568239, -6.33953142228525], [53.3422152, -6.3393308], [53.3423864, -6.338922], [53.3424853, -6.3387315], [53.3425543362028, -6.33859827602172], [53.3425841, -6.338541], [53.342753, -6.3381594], [53.3428848, -6.3377962], [53.3429591, -6.3375621], [53.3430554, -6.3372075], [53.3431026, -6.3369975], [53.3431373, -6.3368433], [53.3431768, -6.3366377], [53.3432332, -6.3362959], [53.3432719, -6.3359653], [53.34329, -6.3357418], [53.3432974, -6.3354654], [53.3432913, -6.3351822], [53.3432729, -6.3348603], [53.3432668, -6.3347932], [53.3432466, -6.3345703], [53.3432032, -6.3342525], [53.3431825, -6.3341386], [53.3431258, -6.3338269], [53.3430423704018, -6.33345460230276], [53.3430126, -6.3333212], [53.3427922, -6.3323805], [53.3427711980603, -6.33229014109212], [53.3427682225934, -6.33227745314216], [53.3426237, -6.3316508], [53.3424158, -6.3307276], [53.3423496, -6.3304223], [53.3422876, -6.3299813], [53.3422362, -6.3294749], [53.3421903, -6.3289236], [53.342217, -6.3284975], [53.3422039, -6.3281247], [53.3421991, -6.3279698], [53.3421891516925, -6.32768019977116], [53.3421549, -6.3266761], [53.3421535, -6.3266322], [53.3421349, -6.3260512], [53.3421456, -6.3253742], [53.3420447, -6.325338], [53.3419383, -6.3252437], [53.3418803, -6.3249931], [53.3417269, -6.3244917], [53.3416341, -6.3241518], [53.3416032, -6.3240149], [53.3415266, -6.3236278], [53.3414851, -6.3232639], [53.341471, -6.3231487], [53.3414624, -6.3229569], [53.3414829, -6.3223001], [53.3415352, -6.3214931], [53.3415594827679, -6.32099131967069], [53.3415662, -6.3208548], [53.3415899, -6.3203677], [53.3416043584467, -6.32010568446113], [53.3416050739209, -6.32009213299919], [53.3416108, -6.3199914], [53.3416379, -6.3194521], [53.3416542, -6.3193357], [53.3416601, -6.3192072], [53.3416221, -6.3191042], [53.3416027, -6.3190518], [53.341539, -6.3189959], [53.3414746, -6.3191342], [53.341416, -6.3192433], [53.3412396, -6.3195441], [53.3411542818252, -6.31969609815086], [53.3410915, -6.3198079], [53.340988, -6.3199546], [53.340871, -6.3200831], [53.3407705, -6.3201504], [53.3406314, -6.3202125], [53.3404852, -6.3202755], [53.3403268, -6.3203933], [53.3401126, -6.3205602], [53.3397278, -6.3208782], [53.3396357, -6.3209479], [53.3395244, -6.321039], [53.3394865, -6.3207727], [53.3394549, -6.3205664], [53.339447, -6.3205098], [53.3393913, -6.3201112], [53.3393738, -6.3200101], [53.3393687, -6.3199306], [53.3393674, -6.3198472], [53.3394073, -6.3196427], [53.3395101, -6.3193039], [53.3395976965262, -6.31901493296853], [53.3396313, -6.3189043], [53.3397285, -6.3185097], [53.3398383696963, -6.31797301642203], [53.3398606, -6.3178653], [53.3400156, -6.3172034], [53.3400677, -6.316981], [53.340081, -6.3169326], [53.3400906, -6.3168792], [53.3401483, -6.3165451], [53.3401724614992, -6.31637962229599], [53.3402647, -6.3157507], [53.3402888, -6.3155624], [53.3403026, -6.3154585], [53.3404092021728, -6.3146676029082], [53.3404110400116, -6.31465361610638], [53.340435, -6.3144763], [53.3405037, -6.3140069], [53.3405468, -6.3137804], [53.3406088, -6.3134287], [53.3406491, -6.3131698], [53.3406866, -6.3128822], [53.3407016, -6.3126821], [53.3407085, -6.3123823], [53.3406735, -6.3117962], [53.3406532, -6.3115175], [53.3406343, -6.3112712], [53.3406104, -6.3110003], [53.3405806, -6.3104457], [53.3405793, -6.3098746], [53.340579, -6.3097328], [53.3405800641905, -6.30968936778539], [53.3405954971867, -6.30910849376959], [53.3405983652759, -6.30900230766641], [53.3406006, -6.3089227], [53.3406192, -6.3081675], [53.3406317, -6.3076594], [53.3406298, -6.3074437], [53.340688, -6.3062908], [53.3406988, -6.3059908], [53.3407206, -6.305383], [53.3407462516582, -6.3046673], [53.3407274, -6.3042036], [53.3407015, -6.3039017], [53.3406936, -6.3036126], [53.3407083, -6.303444], [53.3407162, -6.3033536], [53.3407229, -6.3033034], [53.340779, -6.3028816], [53.3407841, -6.302843], [53.3408991, -6.3020782], [53.3409361, -6.3018323], [53.341021, -6.3012675], [53.3411149, -6.3006497], [53.34114, -6.3004749], [53.3413038, -6.2994858], [53.3413231552661, -6.29932286677473], [53.3413361, -6.2992152], [53.3414002, -6.2986782], [53.3414279956605, -6.29835986996801], [53.3414472, -6.2981404], [53.3414811, -6.297829], [53.3414987, -6.2976774], [53.3415084, -6.2975951], [53.3415619, -6.2973326], [53.3416325, -6.2969566], [53.3418449, -6.2959328], [53.3418953, -6.2957211], [53.341966, -6.2955287], [53.3421256, -6.2950447], [53.3422376865989, -6.2946190666983], [53.342353, -6.2941815], [53.3424392, -6.2939933], [53.3425354, -6.2936196], [53.3426305955312, -6.29319061887518], [53.3426331160912, -6.29317906946684], [53.3427278, -6.2927536], [53.3428119, -6.292346], [53.3429416, -6.2917036], [53.3429987, -6.2914602], [53.3430194, -6.2913608], [53.3430623, -6.2911548], [53.3430709, -6.2911135], [53.3430785, -6.2910731], [53.3430895, -6.2910316], [53.3431064, -6.2909273], [53.3431387, -6.2907251], [53.3431395, -6.2905708], [53.3431434, -6.2905462], [53.3431724, -6.2904124], [53.3432506, -6.2900292], [53.3432784, -6.2899126], [53.3433338, -6.2896959], [53.3433517, -6.2896307], [53.3433658, -6.2895512], [53.3434006, -6.2893545], [53.3434112472688, -6.28919382376084], [53.343429, -6.288927], [53.343445, -6.2887223], [53.3434565944631, -6.28846873644197], [53.3434619, -6.2883533], [53.3434634750518, -6.28832316574999], [53.3434731, -6.2881454], [53.3434815, -6.2879175], [53.3434988, -6.2875824], [53.3435258, -6.2869856], [53.3435303, -6.2868824], [53.3435591, -6.2862805], [53.3435623, -6.2859733], [53.34355, -6.2858], [53.3435451127095, -6.28573309885214], [53.3435287798254, -6.28550118097467], [53.3435233, -6.285423], [53.3435182033699, -6.28535673964109], [53.3434801, -6.284856], [53.3434529, -6.2845799], [53.343448, -6.2845154], [53.343425, -6.2842958], [53.3433938, -6.2837568], [53.3433547, -6.2830145], [53.3433051, -6.2821298], [53.3432565, -6.2816428], [53.3432444, -6.2815223], [53.3432164, -6.2813603], [53.3431839, -6.281212], [53.3431612, -6.2811023], [53.3430972, -6.280792], [53.3430636383866, -6.28062728025778], [53.3430472184375, -6.28054657695164], [53.3429858, -6.2802443], [53.3429186, -6.2798366], [53.3428815, -6.2796082], [53.3428129, -6.2791156], [53.3427928, -6.2784979], [53.3427856, -6.278177], [53.3427853, -6.2779668], [53.3427901, -6.2777499], [53.3427956, -6.2776271], [53.3428047, -6.2775367], [53.3428228, -6.2774154], [53.3428658, -6.2771805], [53.3428815, -6.2771035], [53.3429187, -6.2769237], [53.3429533649268, -6.2767471827057], [53.3429863174742, -6.27657904147538], [53.3429974322268, -6.27652265734362], [53.3430668, -6.2761703], [53.3431279, -6.2760631], [53.3431487, -6.2759823], [53.3431925, -6.2758119], [53.3432656, -6.2755275], [53.3433208, -6.2752478], [53.3433536, -6.2750818], [53.3433743, -6.2748984], [53.3433825, -6.274731], [53.3433957, -6.2744861], [53.3433177, -6.274033], [53.3432568063561, -6.2736791822838], [53.3432488943647, -6.27363334388579], [53.3432278, -6.2735101], [53.3430001, -6.272306], [53.3429686, -6.272072], [53.3429606, -6.2720126], [53.3429554, -6.2719739], [53.3429541, -6.2717643], [53.3430273, -6.2718033], [53.343103, -6.271806], [53.3432234, -6.2717955], [53.3432691, -6.2717978], [53.3433558, -6.2718066], [53.3435403, -6.2718371], [53.3438291, -6.2718104], [53.3439217, -6.2718104], [53.3440782, -6.2718232], [53.3441187, -6.2718304], [53.3441705, -6.2718477], [53.3442044, -6.271859], [53.3443634, -6.2719227], [53.3448894, -6.2720919], [53.3449389, -6.2721078], [53.3449729, -6.2721187], [53.3450464, -6.2721194], [53.3452721, -6.2721566], [53.3455031, -6.2721961], [53.3455433, -6.2722129], [53.3455718, -6.271696], [53.3456239, -6.2712294], [53.3456822, -6.2708075], [53.3457652, -6.270177], [53.3458121, -6.2698238], [53.3459868, -6.2684714], [53.3460364, -6.2680863], [53.3460647, -6.2678683], [53.3461447, -6.2668564], [53.3462557, -6.2657033], [53.3463085, -6.2651481], [53.346319, -6.2650563], [53.3463571, -6.264668], [53.3463946, -6.2643329], [53.3464292, -6.2641007], [53.346473, -6.2638655], [53.346576, -6.2634147], [53.3466205, -6.2632199], [53.3469254, -6.2619049], [53.346997, -6.2615964], [53.3470574, -6.2613238], [53.3471233, -6.2610263], [53.3472135, -6.2606582], [53.3473624, -6.2600576], [53.3474722, -6.2595979], [53.3474831, -6.2595523], [53.3475212, -6.2593927], [53.3475419, -6.2593063], [53.3475525, -6.2592619], [53.3475905, -6.2591013], [53.3476208, -6.2589759], [53.3477048, -6.2586239], [53.3477594, -6.2583905], [53.3477792141368, -6.2582939785727], [53.3479096, -6.2576656], [53.3479201, -6.2576104], [53.3479618, -6.2573793], [53.3479705, -6.2573305], [53.3480063, -6.2571141], [53.3482121, -6.2557574], [53.3482604, -6.2551553], [53.3482797, -6.2549447], [53.3482934, -6.2547718], [53.3482967, -6.2547314], [53.3482904, -6.2541802], [53.3482902172457, -6.25387665047543], [53.3482901378938, -6.25381117175991], [53.3482898, -6.2530001], [53.3482936, -6.2527502], [53.3483092, -6.2521408], [53.3483104, -6.2519893], [53.3483092, -6.2518496], [53.3483086, -6.2517561], [53.3483064, -6.2516236], [53.3483035, -6.2515446], [53.348295, -6.2513894], [53.3482891, -6.251278], [53.3482837, -6.251167], [53.3482782, -6.2510436], [53.3482237259188, -6.25011522745682], [53.3482226892202, -6.25009831588277], [53.3482131, -6.2499334], [53.3481819, -6.2491868], [53.3481527, -6.2488002], [53.348129, -6.2487038], [53.3480955484399, -6.24854671882527], [53.3480909, -6.2484688], [53.3480596, -6.2479357], [53.3480569, -6.2478901], [53.3480351, -6.2475197], [53.3480222, -6.2473009], [53.3480134277266, -6.2471533223723], [53.3480066472749, -6.2470372905805], [53.3479721, -6.2464498], [53.3479635, -6.2463044], [53.3479594, -6.2462345], [53.3479516, -6.2461021], [53.3479413, -6.2459481], [53.3479365, -6.2458779], [53.3478133, -6.2440423], [53.3478044, -6.2439109], [53.3477995, -6.2438382], [53.3477947, -6.2437655], [53.347792, -6.2437256], [53.3477594, -6.2432397], [53.3477026044696, -6.24239614228179], [53.3476827453284, -6.24209966352672], [53.3476787, -6.2420384], [53.3476576, -6.2417239], [53.3476436, -6.2415165], [53.3476397, -6.2414578], [53.3476367, -6.2414143], [53.3476215, -6.2411872], [53.3476116, -6.2410438], [53.3476075, -6.2409839], [53.3476047, -6.2409435], [53.347622, -6.2407317], [53.3476004, -6.2403428], [53.3475841, -6.2401912], [53.3475452, -6.239849], [53.3475413, -6.2397866], [53.3475115, -6.2393091], [53.3474986, -6.2391038], [53.3474859, -6.2389002], [53.3474403, -6.2381696], [53.3474312, -6.2380243], [53.3473639, -6.2368952], [53.3473375694757, -6.23645107778105], [53.3473325537773, -6.2363658915966], [53.3473314960597, -6.23634878337101], [53.3472984, -6.235787], [53.3472944, -6.2357193], [53.3472916, -6.2356714], [53.3472836, -6.2355351], [53.3473315, -6.2355263], [53.3473643, -6.2355202], [53.3474685, -6.2355018], [53.3480874, -6.2353925], [53.3481392, -6.2353834], [53.3481893, -6.2353745], [53.3483429028834, -6.23534765270872], [53.3486244, -6.2352982], [53.3486944, -6.2352859], [53.3487266, -6.2352802], [53.3488022, -6.2352667], [53.3493104, -6.2351791], [53.3496522956078, -6.23511978700673], [53.3502135, -6.2350226], [53.3500869, -6.2330736], [53.3500009, -6.2317365], [53.3495298, -6.2318231], [53.3494249, -6.2318424], [53.349338, -6.231859], [53.3493004, -6.2318653], [53.3489617595632, -6.23192749038566]], "finalStop": {"stopId": "8220DB007890", "stopName": "Castleforbes Road", "stopCode": "7890", "lat": 53.348964, "lon": -6.231907, "stopSequence": 50, "arrivalTime": "05:51:49", "departureTime": "05:51:49"}}], "tripIds": ["5332_22817", "5332_22820", "5332_22823", "5332_22826", "5332_22827", "5332_22831", "5332_22833", "5332_22837", "5332_22838", "5332_22841", "5332_22844", "5332_22847", "5332_22850", "5332_22853", "5332_22856", "5332_22860", "5332_22862", "5332_22867", "5332_22869", "5332_22874", "5332_22877", "5332_22880", "5332_22884", "5332_22888", "5332_22892", "5332_22896", "5332_22899", "5332_22905", "5332_22908", "5332_22912", "5332_22916", "5332_22920", "5332_22923", "5332_22927", "5332_22930", "5332_22934", "5332_22937", "5332_22941", "5332_22944", "5332_22948", "5332_22953", "5332_22956", "5332_22961", "5332_22964", "5332_22967", "5332_22970", "5332_22973", "5332_22977", "5332_22982", "5332_22984", "5332_22987", "5332_22990", "5332_22995", "5332_22996", "5332_23001", "5332_23004", "5332_23007", "5332_23011", "5332_23016", "5332_23019", "5332_23021", "5332_23025", "5332_23028", "5332_23031", "5332_23035", "5332_23038", "5332_23042", "5332_23044", "5332_23048", "5332_23050", "5332_23055", "5332_23056", "5332_23061", "5332_23064", "5332_23068", "5332_23070", "5332_23071", "5332_23074", "5332_23075", "5332_23078", "5332_23079", "5332_23082", "5332_23083", "5332_23086", "5332_23087", "5332_23089", "5332_23090", "5332_23095", "5332_23097", "5332_23100", "5332_23104", "5332_23105", "5332_23108", "5332_23111", "5332_23115", "5332_23117", "5332_23120", "5332_23121", "5332_23125", "5332_23126", "5332_23130", "5332_23133", "5332_23135", "5332_23139", "5332_23141", "5332_23145", "5332_23148", "5332_23152", "5332_23155", "5332_23159", "5332_23164", "5332_23167", "5332_23171", "5332_23174", "5332_23180", "5332_23184", "5332_23187", "5332_23190", "5332_23195", "5332_23199", "5332_23202", "5332_23205", "5332_23210", "5332_23214", "5332_23218", "5332_23221", "5332_23224", "5332_23228", "5332_23231", "5332_23234", "5332_23238", "5332_23242", "5332_23245", "5332_23249", "5332_23254", "5332_23256", "5332_23260", "5332_23262", "5332_23266", "5332_23270", "5332_23274", "5332_23278", "5332_23280", "5332_23283", "5332_23287", "5332_23290", "5332_23294", "5332_23297", "5332_23301", "5332_23304", "5332_23308", "5332_23310", "5332_23314", "5332_23318", "5332_23320", "5332_23324", "5332_23326", "5332_23331", "5332_23334", "5332_23337", "5332_23340", "5332_23344", "5332_23346", "5332_23351", "5332_23354", "5332_23355", "5332_23359", "5332_23360", "5332_23363", "5332_23364", "5332_23367", "5332_23368", "5332_23370", "5332_23371", "5333_22831", "5333_22832", "5333_22833", "5333_22834", "5333_22835", "5333_22836", "5333_22837", "5333_22838", "5333_22839", "5333_22840", "5333_22841", "5333_22842", "5333_22843", "5333_22844", "5333_22845", "5333_22846", "5333_22847", "5333_22848", "5333_22849", "5333_22850", "5333_22851", "5333_22852", "5333_22853", "5333_22854", "5333_22855", "5333_22856", "5333_22857", "5333_22858", "5333_22859", "5333_22860", "5333_22861", "5333_22862", "5333_22863", "5333_22864", "5333_22865", "5333_22866", "5333_22867", "5333_22868", "5333_22869", "5333_22870", "5333_22871", "5333_22872", "5333_22873", "5333_22874", "5333_22875", "5333_22876", "5333_22877", "5333_22878", "5333_22879", "5333_22880", "5333_22881", "5333_22882", "5333_22883", "5333_22884", "5333_22885", "5333_22886", "5333_22887", "5333_22888", "5333_22889", "5333_22890", "5333_22891", "5333_22892", "5333_22893", "5333_22894", "5333_22895", "5333_22896", "5333_22897", "5333_22898", "5333_22899", "5333_22900", "5333_22901", "5333_22902", "5333_22903", "5333_22904", "5333_22905", "5333_22906", "5333_22907", "5333_22908", "5333_22909", "5333_22910", "5333_22911", "5333_22912", "5333_22913", "5333_22914", "5333_22915", "5333_22916", "5333_22917", "5333_22918", "5333_22919", "5333_22920", "5333_22921", "5333_22922", "5333_22923", "5333_22924", "5333_22925", "5333_22926", "5333_22927", "5333_22928", "5333_22929", "5333_22930", "5333_22931", "5333_22932", "5333_22933", "5333_22934", "5333_22935", "5333_22936", "5333_22937", "5333_22938", "5333_22939", "5333_22940", "5333_22941", "5333_22942", "5333_22943", "5333_22944", "5333_22945", "5333_22946", "5333_22947", "5333_22948", "5333_22949", "5333_22950", "5333_22951", "5333_22952", "5333_22953", "5333_22954", "5333_22955", "5333_22956", "5333_22957", "5333_22958", "5333_22959", "5333_22960", "5333_22961", "5333_22962", "5333_22963", "5333_22964", "5333_22965", "5333_22966", "5333_22967", "5333_22968", "5333_22969", "5333_22970", "5333_22971", "5333_22972", "5333_22973", "5333_22974", "5333_22975", "5333_22976", "5333_22977", "5333_22978", "5333_22979", "5333_22980", "5333_22981", "5333_22982", "5333_22983", "5333_22984", "5333_22985", "5333_22986", "5333_22987", "5333_22988", "5333_22989", "5333_22990", "5333_22991", "5333_22992", "5333_22993", "5333_22994", "5333_22995", "5333_22996", "5333_22997", "5333_22998", "5333_22999", "5333_23000", "5333_23001", "5333_23002", "5333_23003", "5333_23004", "5333_23005", "5333_23006", "5333_23007", "5333_23008", "5333_23009", "5333_23010", "5333_23011", "5333_23012", "5333_23013", "5333_23014", "5333_23015", "5333_23016", "5333_23017", "5333_23018", "5333_23019", "5333_23020", "5333_23021", "5333_23022", "5333_23023", "5333_23024", "5333_23025", "5333_23026", "5333_23027", "5333_23028", "5333_23029", "5333_23030", "5333_23031", "5333_23032", "5333_23033", "5333_23034", "5333_23035", "5333_23036", "5333_23037", "5333_23038", "5333_23039", "5333_23040", "5333_23041", "5333_23042", "5333_23043", "5333_23044", "5333_23045", "5333_23046", "5333_23047", "5333_23048", "5333_23049", "5333_23050", "5333_23051", "5333_23052", "5333_23053", "5333_23054", "5333_23055", "5333_23056", "5333_23057", "5333_23058", "5333_23059", "5333_23060", "5333_23061", "5333_23062", "5333_23063", "5333_23064", "5333_23065", "5333_23066", "5333_23067", "5333_23068", "5333_23069", "5333_23070", "5333_23071", "5333_23072", "5333_23073", "5333_23074", "5333_23075", "5333_23076", "5333_23077", "5333_23078", "5333_23079", "5333_23080", "5333_23081", "5333_23082", "5333_23083", "5333_23084", "5333_23085", "5333_23086", "5333_23087", "5333_23088", "5333_23089", "5333_23090", "5333_23091", "5333_23092", "5333_23093", "5333_23094", "5333_23095", "5333_23096", "5333_23097", "5333_23098", "5333_23099", "5333_23100", "5333_23101", "5333_23102", "5333_23103", "5333_23104", "5333_23105", "5333_23106", "5333_23107", "5333_23108", "5333_23109", "5333_23110", "5333_23111", "5333_23112", "5333_23113", "5333_23114", "5333_23115", "5333_23116", "5333_23117", "5333_23118", "5333_23119", "5333_23120", "5333_23121", "5333_23122", "5333_23123", "5333_23124", "5333_23125", "5333_23126", "5333_23127", "5333_23128", "5333_23129", "5333_23130", "5333_23131", "5333_23132", "5333_23133", "5333_23134", "5333_23135", "5333_23136", "5333_23137", "5333_23138", "5333_23139", "5333_23140", "5333_23141", "5333_23142", "5333_23143", "5333_23144", "5333_23145", "5333_23146", "5333_23147", "5333_23148", "5333_23149", "5333_23150", "5333_23151", "5333_23152", "5333_23153", "5333_23154", "5333_23155", "5333_23156", "5333_23157", "5333_23158", "5333_23159", "5333_23160", "5333_23161", "5333_23162", "5333_23163", "5333_23164", "5333_23165", "5333_23166", "5333_23167", "5333_23168", "5333_23169", "5333_23170", "5333_23171", "5333_23172", "5333_23173", "5333_23174", "5333_23175", "5333_23176", "5333_23177", "5333_23178", "5333_23179", "5333_23180", "5333_23181", "5333_23182", "5333_23183", "5333_23184", "5333_23185", "5333_23186", "5333_23187", "5333_23188", "5333_23189", "5333_23190", "5333_23191", "5333_23192", "5333_23193", "5333_23194", "5333_23195", "5333_23196", "5333_23197", "5333_23198", "5333_23199", "5333_23200", "5333_23201", "5333_23202", "5333_23203", "5333_23204", "5333_23205", "5333_23206", "5333_23207", "5333_23208", "5333_23209", "5333_23210", "5333_23211", "5333_23212", "5333_23213", "5333_23214", "5333_23215", "5333_23216", "5333_23217", "5333_23218", "5333_23219", "5333_23220", "5333_23221", "5333_23222", "5333_23223", "5333_23224", "5333_23225", "5333_23226", "5333_23227", "5333_23228", "5333_23229", "5333_23230", "5333_23231", "5333_23232", "5333_23233", "5333_23234", "5333_23235", "5333_23236", "5333_23237", "5333_23238", "5333_23239", "5333_23240", "5333_23241", "5333_23242", "5333_23243", "5333_23244", "5333_23245", "5333_23246", "5333_23247", "5333_23248", "5333_23249", "5333_23250", "5333_23251", "5333_23252", "5333_23253", "5333_23254", "5333_23255", "5333_23256", "5333_23257", "5333_23258", "5333_23259", "5333_23260", "5333_23261", "5333_23262", "5333_23263", "5333_23264", "5333_23265", "5333_23266", "5333_23267", "5333_23268", "5333_23269", "5333_23270", "5333_23271", "5333_23272", "5333_23273", "5333_23274", "5333_23275", "5333_23276", "5333_23277", "5333_23278", "5333_23279", "5333_23280", "5333_23281", "5333_23282", "5333_23283", "5333_23284", "5333_23285", "5333_23286", "5333_23287", "5333_23288", "5333_23289", "5333_23290", "5333_23291", "5333_23292", "5333_23293", "5333_23294", "5333_23295", "5333_23296", "5333_23297", "5333_23298", "5333_23299", "5333_23300", "5333_23301", "5333_23302", "5333_23303", "5333_23304", "5333_23305", "5333_23306", "5333_23307", "5333_23308", "5333_23309", "5333_23310", "5333_23311", "5333_23312", "5333_23313", "5333_23314", "5333_23315", "5333_23316", "5333_23317", "5333_23318", "5333_23319", "5333_23320", "5333_23321", "5333_23322", "5333_23323", "5333_23324", "5333_23325", "5333_23326", "5333_23327", "5333_23328", "5333_23329", "5333_23330", "5333_23331", "5333_23332", "5333_23333", "5333_23334", "5333_23335", "5333_23336", "5333_23337", "5333_23338", "5333_23339", "5333_23340", "5333_23341", "5333_23342", "5333_23343", "5333_23344", "5333_23345", "5333_23346", "5333_23347", "5333_23348", "5333_23349", "5333_23350", "5333_23351", "5333_23352", "5333_23353", "5333_23354", "5333_23355", "5333_23356", "5333_23357", "5333_23358", "5333_23359", "5333_23360", "5333_23361", "5333_23362", "5333_23363", "5333_23364", "5333_23365", "5333_23366", "5333_23367", "5333_23368", "5333_23369", "5333_23370", "5333_23371", "5333_23372", "5333_23373", "5333_23374", "5333_23375", "5333_23376", "5333_23377", "5333_23378", "5333_23379", "5333_23380", "5333_23381", "5333_23382", "5333_23383", "5333_23384", "5333_23385", "5333_23386", "5333_23387", "5333_23388", "5353_26993", "5353_26994", "5353_26995", "5353_26996", "5353_26997", "5353_26998", "5353_26999", "5353_27000", "5353_27001", "5353_27002", "5353_27003", "5353_27004", "5353_27005", "5353_27006", "5353_27007", "5353_27008", "5353_27009", "5353_27010", "5353_27011", "5353_27012", "5353_27013", "5353_27014", "5353_27015", "5353_27016", "5353_27017", "5353_27018", "5353_27019", "5353_27020", "5353_27021", "5353_27022", "5353_27023", "5353_27024", "5353_27025", "5353_27026", "5353_27027", "5353_27028", "5353_27029", "5353_27030", "5353_27031", "5353_27032", "5353_27033", "5353_27034", "5353_27035", "5353_27036", "5353_27037", "5353_27038", "5353_27039", "5353_27040", "5353_27041", "5353_27042", "5353_27043", "5353_27044", "5353_27045", "5353_27046", "5353_27047", "5353_27048", "5353_27049", "5353_27050", "5353_27051", "5353_27052", "5353_27053", "5353_27054", "5353_27055", "5353_27056", "5353_27057", "5353_27058", "5353_27059", "5353_27060", "5353_27061", "5353_27062", "5353_27063", "5353_27064", "5353_27065", "5353_27066", "5353_27067", "5353_27068", "5353_27069", "5353_27070", "5353_27071", "5353_27072", "5353_27073", "5353_27074", "5353_27075", "5353_27076", "5353_27077", "5353_27078", "5353_27079", "5353_27080", "5353_27081", "5353_27082", "5353_27083", "5353_27084", "5353_27085", "5353_27086", "5353_27087", "5353_27088", "5353_27089", "5353_27090", "5353_27091", "5353_27092", "5353_27093", "5353_27094", "5353_27095", "5353_27096", "5353_27097", "5353_27098", "5353_27099", "5353_27100", "5353_27101", "5353_27102", "5353_27103", "5353_27104", "5353_27105", "5353_27106", "5353_27107", "5353_27108", "5353_27109", "5353_27110", "5353_27111", "5353_27112", "5353_27113", "5353_27114", "5353_27115", "5353_27116", "5353_27117", "5353_27118", "5353_27119", "5353_27120", "5353_27121", "5353_27122", "5353_27123", "5353_27124", "5353_27125", "5353_27126", "5353_27127", "5353_27128", "5353_27129", "5353_27130", "5353_27131", "5353_27132", "5353_27133", "5353_27134", "5353_27135", "5353_27136", "5353_27137", "5353_27138", "5353_27139", "5353_27140", "5353_27141", "5353_27142", "5353_27143", "5353_27144", "5353_27145", "5353_27146", "5353_27147", "5353_27148", "5353_27149", "5353_27150", "5353_27151", "5353_27152", "5353_27153", "5353_27154", "5353_27155", "5353_27156", "5353_27157", "5353_27158", "5353_27159", "5353_27160", "5353_27161", "5353_27162", "5353_27163", "5353_27164", "5353_27165", "5353_27166", "5353_27167", "5353_27168", "5353_27169", "5353_27170", "5353_27171", "5353_27172", "5353_27173", "5353_27174", "5353_27175", "5353_27176", "5353_27177", "5353_27178", "5353_27179", "5353_27180", "5353_27181", "5353_27182", "5353_27183", "5353_27184", "5353_27185", "5353_27186", "5353_27187", "5353_27188", "5353_27189", "5353_27190", "5353_27191", "5353_27192", "5353_27193", "5353_27194", "5353_27195", "5353_27196", "5353_27197", "5353_27198", "5353_27199", "5353_27200", "5353_27201", "5353_27202", "5353_27203", "5353_27204", "5353_27205", "5353_27206", "5353_27207", "5353_27208", "5353_27209", "5353_27210", "5353_27211", "5353_27212", "5353_27213", "5353_27214", "5353_27215", "5353_27216", "5353_27217", "5353_27218", "5353_27219", "5353_27220", "5353_27221", "5353_27222", "5353_27223", "5353_27224", "5353_27225", "5353_27226", "5353_27227", "5353_27228", "5353_27229", "5353_27230", "5353_27231", "5353_27232", "5353_27233", "5353_27234", "5353_27235", "5353_27236", "5353_27237", "5353_27238", "5353_27239", "5353_27240", "5353_27241", "5353_27242", "5353_27243", "5353_27244", "5353_27245", "5353_27246", "5353_27247", "5353_27248", "5353_27249", "5353_27250", "5353_27251", "5353_27252", "5353_27253", "5353_27254", "5353_27255", "5353_27256", "5353_27257", "5353_27258", "5353_27259", "5353_27260", "5353_27261", "5353_27262", "5353_27263", "5353_27264", "5353_27265", "5353_27266", "5353_27267", "5353_27268", "5353_27269", "5353_27270", "5353_27271", "5353_27272", "5353_27273", "5353_27274", "5353_27275", "5353_27276", "5353_27277", "5353_27278", "5353_27279", "5353_27280", "5353_27281", "5353_27282", "5353_27283", "5353_27284", "5353_27285", "5353_27286", "5353_27287", "5353_27288", "5353_27289", "5353_27290", "5353_27291", "5353_27292", "5353_27293", "5353_27294", "5353_27295", "5353_27296", "5353_27297", "5353_27298", "5353_27299", "5353_27300", "5353_27301", "5353_27302", "5353_27303", "5353_27304", "5353_27305", "5353_27306", "5353_27307", "5353_27308", "5353_27309", "5353_27310", "5353_27311", "5353_27312", "5353_27313", "5353_27314", "5353_27315", "5353_27316", "5353_27317", "5353_27318", "5353_27319", "5353_27320", "5353_27321", "5353_27322", "5353_27323", "5353_27324", "5353_27325", "5353_27326", "5353_27327", "5353_27328", "5353_27329", "5353_27330", "5353_27331", "5353_27332", "5353_27333", "5353_27334", "5353_27335", "5353_27336", "5353_27337", "5353_27338", "5353_27339", "5353_27340", "5353_27341", "5353_27342", "5353_27343", "5353_27344", "5353_27345", "5353_27346", "5353_27347", "5353_27348", "5353_27349", "5353_27350", "5353_27351", "5353_27352", "5353_27353", "5353_27354", "5353_27355", "5353_27356", "5353_27357", "5353_27358", "5353_27359", "5353_27360", "5353_27361", "5353_27362", "5353_27363", "5353_27364", "5353_27365", "5353_27366", "5353_27367", "5353_27368", "5353_27369", "5353_27370", "5353_27371", "5353_27372", "5353_27373", "5353_27374", "5353_27375", "5353_27376", "5353_27377", "5353_27378", "5353_27379", "5353_27380", "5353_27381", "5353_27382", "5353_27383", "5353_27384", "5353_27385", "5353_27386", "5353_27387", "5353_27388", "5353_27389", "5353_27390", "5353_27391", "5353_27392", "5353_27393", "5353_27394", "5353_27395", "5353_27396", "5353_27397", "5353_27398", "5353_27399", "5353_27400", "5353_27401", "5353_27402", "5353_27403", "5353_27404", "5353_27405", "5353_27406", "5353_27407", "5353_27408", "5353_27409", "5353_27410", "5353_27411", "5353_27412", "5353_27413", "5353_27414", "5353_27415", "5353_27416", "5353_27417", "5353_27418", "5353_27419", "5353_27420", "5353_27421", "5353_27422", "5353_27423", "5353_27424", "5353_27425", "5353_27426", "5353_27427", "5353_27428", "5353_27429", "5353_27430", "5353_27431", "5353_27432", "5353_27433", "5353_27434", "5353_27435", "5353_27436", "5353_27437", "5353_27438", "5353_27439", "5353_27440", "5353_27441", "5353_27442", "5353_27443", "5353_27444", "5353_27445", "5353_27446", "5353_27447", "5353_27448", "5353_27449", "5353_27450", "5353_27451", "5353_27452", "5353_27453", "5353_27454", "5353_27455", "5353_27456", "5353_27457", "5353_27458", "5353_27459", "5353_27460", "5353_27461", "5353_27462", "5353_27463", "5353_27464", "5353_27465", "5353_27466", "5353_27467", "5353_27468", "5353_27469", "5353_27470", "5353_27471", "5353_27472", "5353_27473", "5353_27474", "5353_27475", "5353_27476", "5353_27477", "5353_27478", "5353_27479", "5353_27480", "5353_27481", "5353_27482", "5353_27483", "5353_27484", "5353_27485", "5353_27486", "5353_27487", "5353_27488", "5353_27489", "5353_27490", "5353_27491", "5353_27492", "5353_27493", "5353_27494", "5353_27495", "5353_27496", "5353_27497", "5353_27498", "5353_27499", "5353_27500", "5353_27501", "5353_27502", "5353_27503", "5353_27504", "5353_27505", "5353_27506", "5353_27507", "5353_27508", "5353_27509", "5353_27510", "5353_27511", "5353_27512", "5353_27513", "5353_27514", "5353_27515", "5353_27516", "5353_27517", "5353_27518", "5353_27519", "5353_27520", "5353_27521", "5353_27522", "5353_27523", "5353_27524", "5353_27525", "5353_27526", "5353_27527", "5353_27528", "5353_27529", "5353_27530", "5353_27531", "5353_27532", "5353_27533", "5353_27534", "5353_27535", "5353_27536", "5353_27537", "5353_27538", "5353_27539", "5353_27540", "5353_27541", "5353_27542", "5353_27543", "5353_27544", "5353_27545", "5353_27546", "5353_27547", "5353_27548", "5353_27549", "5353_27550", "5353_27551", "5353_27552", "5353_27553", "5353_27554", "5353_27555", "5353_27556", "5353_27557", "5353_27558", "5353_27559", "5353_27560", "5353_27561", "5353_27562", "5353_27563", "5353_27564", "5353_27565", "5353_27566", "5353_27567", "5353_27568", "5353_27569", "5353_27570", "5353_27571", "5353_27572", "5353_27573", "5353_27574", "5353_27575", "5353_27576", "5353_27577", "5353_27578", "5353_27579", "5353_27580", "5353_27581", "5353_27582", "5353_27583", "5353_27584", "5353_27585", "5353_27586", "5353_27587", "5353_27588", "5353_27589", "5353_27590", "5353_27591", "5353_27592", "5353_27593", "5353_27594", "5353_27595", "5353_27596", "5353_27597", "5353_27598", "5353_27599", "5353_27600", "5353_27601", "5353_27602", "5353_27603", "5353_27604", "5353_27605", "5353_27606", "5353_27607", "5353_27608", "5353_27609", "5353_27610", "5353_27611", "5353_27612", "5353_27613", "5353_27614", "5353_27615", "5353_27616", "5353_27617", "5353_27618", "5353_27619", "5353_27620", "5353_27621", "5353_27622", "5353_27623", "5353_27624", "5353_27625", "5353_27626", "5353_27627", "5353_27628", "5353_27629", "5353_27630", "5353_27631", "5353_27632", "5353_27633", "5353_27634", "5353_27635", "5353_27636", "5353_27637", "5353_27638", "5353_27639", "5353_27640", "5353_27641", "5353_27642", "5353_27643", "5353_27644", "5353_27645", "5353_27646", "5353_27647", "5353_27648"]}